Buildfile: C:\Users\jovan\OneDrive\Desktop\ETF HELL\77777 SEMESTAR\prevodioci\projekat\workspace\MJCompiler\build.xml

disasm:
     [java] codeSize=4483
     [java] dataSize=335
     [java] mainPC=669
     [java] 0: enter 1 1
     [java] 3: load_0
     [java] 4: arraylength
     [java] 5: exit
     [java] 6: return
     [java] 7: enter 1 1
     [java] 10: load_0
     [java] 11: const 256
     [java] 16: rem
     [java] 17: exit
     [java] 18: return
     [java] 19: enter 1 1
     [java] 22: load_0
     [java] 23: exit
     [java] 24: return
     [java] 25: enter 1 1
     [java] 28: const 112
     [java] 33: const_1
     [java] 34: bprint
     [java] 35: const 105
     [java] 40: const_1
     [java] 41: bprint
     [java] 42: const 10
     [java] 47: const_1
     [java] 48: bprint
     [java] 49: exit
     [java] 50: return
     [java] 51: enter 1 1
     [java] 54: load_0
     [java] 55: load_0
     [java] 56: getfield 0
     [java] 59: invokevirtual hi
     [java] 72: exit
     [java] 73: return
     [java] 74: enter 2 2
     [java] 77: load_0
     [java] 78: load_1
     [java] 79: putfield 3
     [java] 82: exit
     [java] 83: return
     [java] 84: enter 1 1
     [java] 87: load_0
     [java] 88: read
     [java] 89: putfield 3
     [java] 92: exit
     [java] 93: return
     [java] 94: enter 1 1
     [java] 97: const_0
     [java] 98: exit
     [java] 99: return
     [java] 100: trap 0
     [java] 102: enter 1 1
     [java] 105: load_0
     [java] 106: load_0
     [java] 107: getfield 0
     [java] 110: invokevirtual zapremina
     [java] 151: load_0
     [java] 152: getfield 3
     [java] 155: mul
     [java] 156: exit
     [java] 157: return
     [java] 158: trap 0
     [java] 160: enter 2 2
     [java] 163: load_0
     [java] 164: load_1
     [java] 165: putfield 4
     [java] 168: exit
     [java] 169: return
     [java] 170: enter 1 1
     [java] 173: load_0
     [java] 174: getfield 4
     [java] 177: exit
     [java] 178: return
     [java] 179: trap 0
     [java] 181: enter 1 1
     [java] 184: load_0
     [java] 185: getfield 3
     [java] 188: exit
     [java] 189: return
     [java] 190: trap 0
     [java] 192: enter 2 2
     [java] 195: load_1
     [java] 196: const 1234
     [java] 201: putfield 3
     [java] 204: load_1
     [java] 205: getfield 3
     [java] 208: const_5
     [java] 209: print
     [java] 210: exit
     [java] 211: return
     [java] 212: enter 1 1
     [java] 215: const 115
     [java] 220: const_1
     [java] 221: bprint
     [java] 222: const 105
     [java] 227: const_1
     [java] 228: bprint
     [java] 229: const 10
     [java] 234: const_1
     [java] 235: bprint
     [java] 236: exit
     [java] 237: return
     [java] 238: enter 2 2
     [java] 241: load_0
     [java] 242: load_1
     [java] 243: putfield 3
     [java] 246: exit
     [java] 247: return
     [java] 248: enter 2 2
     [java] 251: load_0
     [java] 252: load_1
     [java] 253: putfield 5
     [java] 256: load_0
     [java] 257: const 115
     [java] 262: load_0
     [java] 263: getfield 0
     [java] 266: invokevirtual postaviVrstu
     [java] 319: exit
     [java] 320: return
     [java] 321: enter 1 2
     [java] 324: const_4
     [java] 325: store_1
     [java] 326: load_1
     [java] 327: load_0
     [java] 328: getfield 5
     [java] 331: const_3
     [java] 332: div
     [java] 333: mul
     [java] 334: exit
     [java] 335: return
     [java] 336: trap 0
     [java] 338: enter 1 1
     [java] 341: const 107
     [java] 346: const_1
     [java] 347: bprint
     [java] 348: const 105
     [java] 353: const_1
     [java] 354: bprint
     [java] 355: const 10
     [java] 360: const_1
     [java] 361: bprint
     [java] 362: exit
     [java] 363: return
     [java] 364: enter 2 2
     [java] 367: load_0
     [java] 368: load_1
     [java] 369: putfield 3
     [java] 372: exit
     [java] 373: return
     [java] 374: enter 4 4
     [java] 377: load_0
     [java] 378: load_1
     [java] 379: putfield 5
     [java] 382: load_0
     [java] 383: load_2
     [java] 384: putfield 6
     [java] 387: load_0
     [java] 388: load_3
     [java] 389: putfield 7
     [java] 392: load_0
     [java] 393: const 107
     [java] 398: putfield 4
     [java] 401: exit
     [java] 402: return
     [java] 403: enter 1 2
     [java] 406: load_0
     [java] 407: getfield 5
     [java] 410: load_0
     [java] 411: getfield 6
     [java] 414: mul
     [java] 415: load_0
     [java] 416: getfield 7
     [java] 419: mul
     [java] 420: store_1
     [java] 421: load_1
     [java] 422: exit
     [java] 423: return
     [java] 424: trap 0
     [java] 426: enter 2 2
     [java] 429: load_1
     [java] 430: const 4444
     [java] 435: putfield 3
     [java] 438: load_1
     [java] 439: getfield 3
     [java] 442: const_5
     [java] 443: print
     [java] 444: load_1
     [java] 445: load_1
     [java] 446: getfield 0
     [java] 449: invokevirtual hiThis
     [java] 478: exit
     [java] 479: return
     [java] 480: enter 1 1
     [java] 483: load_0
     [java] 484: load_0
     [java] 485: getfield 0
     [java] 488: invokevirtual dohvVrstu
     [java] 529: const 115
     [java] 534: jne 13 (=547)
     [java] 537: const 83
     [java] 542: const_1
     [java] 543: bprint
     [java] 544: jmp 64 (=608)
     [java] 547: load_0
     [java] 548: load_0
     [java] 549: getfield 0
     [java] 552: invokevirtual dohvVrstu
     [java] 593: const 107
     [java] 598: jne 10 (=608)
     [java] 601: const 75
     [java] 606: const_1
     [java] 607: bprint
     [java] 608: const 10
     [java] 613: const_1
     [java] 614: bprint
     [java] 615: load_0
     [java] 616: load_0
     [java] 617: getfield 0
     [java] 620: invokevirtual dohvTezinu
     [java] 665: const_5
     [java] 666: print
     [java] 667: exit
     [java] 668: return
     [java] 669: const 104
     [java] 674: putstatic 4
     [java] 677: const 105
     [java] 682: putstatic 5
     [java] 685: const_m1
     [java] 686: putstatic 6
     [java] 689: const 25
     [java] 694: putstatic 7
     [java] 697: const 104
     [java] 702: putstatic 8
     [java] 705: const 105
     [java] 710: putstatic 9
     [java] 713: const 84
     [java] 718: putstatic 10
     [java] 721: const 104
     [java] 726: putstatic 11
     [java] 729: const 105
     [java] 734: putstatic 12
     [java] 737: const 115
     [java] 742: putstatic 13
     [java] 745: const_m1
     [java] 746: putstatic 14
     [java] 749: const 51
     [java] 754: putstatic 15
     [java] 757: const 112
     [java] 762: putstatic 16
     [java] 765: const 111
     [java] 770: putstatic 17
     [java] 773: const 115
     [java] 778: putstatic 18
     [java] 781: const 116
     [java] 786: putstatic 19
     [java] 789: const 97
     [java] 794: putstatic 20
     [java] 797: const 118
     [java] 802: putstatic 21
     [java] 805: const 105
     [java] 810: putstatic 22
     [java] 813: const 84
     [java] 818: putstatic 23
     [java] 821: const 101
     [java] 826: putstatic 24
     [java] 829: const 122
     [java] 834: putstatic 25
     [java] 837: const 105
     [java] 842: putstatic 26
     [java] 845: const 110
     [java] 850: putstatic 27
     [java] 853: const 117
     [java] 858: putstatic 28
     [java] 861: const_m1
     [java] 862: putstatic 29
     [java] 865: const 74
     [java] 870: putstatic 30
     [java] 873: const 117
     [java] 878: putstatic 31
     [java] 881: const 99
     [java] 886: putstatic 32
     [java] 889: const 105
     [java] 894: putstatic 33
     [java] 897: const 116
     [java] 902: putstatic 34
     [java] 905: const 97
     [java] 910: putstatic 35
     [java] 913: const 106
     [java] 918: putstatic 36
     [java] 921: const 84
     [java] 926: putstatic 37
     [java] 929: const 101
     [java] 934: putstatic 38
     [java] 937: const 122
     [java] 942: putstatic 39
     [java] 945: const 105
     [java] 950: putstatic 40
     [java] 953: const 110
     [java] 958: putstatic 41
     [java] 961: const 117
     [java] 966: putstatic 42
     [java] 969: const_m1
     [java] 970: putstatic 43
     [java] 973: const 84
     [java] 978: putstatic 44
     [java] 981: const 122
     [java] 986: putstatic 45
     [java] 989: const 97
     [java] 994: putstatic 46
     [java] 997: const 112
     [java] 1002: putstatic 47
     [java] 1005: const 114
     [java] 1010: putstatic 48
     [java] 1013: const 101
     [java] 1018: putstatic 49
     [java] 1021: const 109
     [java] 1026: putstatic 50
     [java] 1029: const 105
     [java] 1034: putstatic 51
     [java] 1037: const 110
     [java] 1042: putstatic 52
     [java] 1045: const 97
     [java] 1050: putstatic 53
     [java] 1053: const_m1
     [java] 1054: putstatic 54
     [java] 1057: const 94
     [java] 1062: putstatic 55
     [java] 1065: const 81
     [java] 1070: putstatic 56
     [java] 1073: const_m1
     [java] 1074: putstatic 57
     [java] 1077: const 102
     [java] 1082: putstatic 58
     [java] 1085: const 112
     [java] 1090: putstatic 59
     [java] 1093: const 111
     [java] 1098: putstatic 60
     [java] 1101: const 115
     [java] 1106: putstatic 61
     [java] 1109: const 116
     [java] 1114: putstatic 62
     [java] 1117: const 97
     [java] 1122: putstatic 63
     [java] 1125: const 118
     [java] 1130: putstatic 64
     [java] 1133: const 105
     [java] 1138: putstatic 65
     [java] 1141: const 86
     [java] 1146: putstatic 66
     [java] 1149: const 114
     [java] 1154: putstatic 67
     [java] 1157: const 115
     [java] 1162: putstatic 68
     [java] 1165: const 116
     [java] 1170: putstatic 69
     [java] 1173: const 117
     [java] 1178: putstatic 70
     [java] 1181: const_m1
     [java] 1182: putstatic 71
     [java] 1185: const 160
     [java] 1190: putstatic 72
     [java] 1193: const 100
     [java] 1198: putstatic 73
     [java] 1201: const 111
     [java] 1206: putstatic 74
     [java] 1209: const 104
     [java] 1214: putstatic 75
     [java] 1217: const 118
     [java] 1222: putstatic 76
     [java] 1225: const 86
     [java] 1230: putstatic 77
     [java] 1233: const 114
     [java] 1238: putstatic 78
     [java] 1241: const 115
     [java] 1246: putstatic 79
     [java] 1249: const 116
     [java] 1254: putstatic 80
     [java] 1257: const 117
     [java] 1262: putstatic 81
     [java] 1265: const_m1
     [java] 1266: putstatic 82
     [java] 1269: const 170
     [java] 1274: putstatic 83
     [java] 1277: const 100
     [java] 1282: putstatic 84
     [java] 1285: const 111
     [java] 1290: putstatic 85
     [java] 1293: const 104
     [java] 1298: putstatic 86
     [java] 1301: const 118
     [java] 1306: putstatic 87
     [java] 1309: const 84
     [java] 1314: putstatic 88
     [java] 1317: const 101
     [java] 1322: putstatic 89
     [java] 1325: const 122
     [java] 1330: putstatic 90
     [java] 1333: const 105
     [java] 1338: putstatic 91
     [java] 1341: const 110
     [java] 1346: putstatic 92
     [java] 1349: const 117
     [java] 1354: putstatic 93
     [java] 1357: const_m1
     [java] 1358: putstatic 94
     [java] 1361: const 181
     [java] 1366: putstatic 95
     [java] 1369: const 104
     [java] 1374: putstatic 96
     [java] 1377: const 105
     [java] 1382: putstatic 97
     [java] 1385: const 114
     [java] 1390: putstatic 98
     [java] 1393: const_m1
     [java] 1394: putstatic 99
     [java] 1397: const 192
     [java] 1402: putstatic 100
     [java] 1405: const -2
     [java] 1410: putstatic 101
     [java] 1413: const 104
     [java] 1418: putstatic 102
     [java] 1421: const 105
     [java] 1426: putstatic 103
     [java] 1429: const_m1
     [java] 1430: putstatic 104
     [java] 1433: const 212
     [java] 1438: putstatic 105
     [java] 1441: const 112
     [java] 1446: putstatic 106
     [java] 1449: const 111
     [java] 1454: putstatic 107
     [java] 1457: const 115
     [java] 1462: putstatic 108
     [java] 1465: const 116
     [java] 1470: putstatic 109
     [java] 1473: const 97
     [java] 1478: putstatic 110
     [java] 1481: const 118
     [java] 1486: putstatic 111
     [java] 1489: const 105
     [java] 1494: putstatic 112
     [java] 1497: const 84
     [java] 1502: putstatic 113
     [java] 1505: const 101
     [java] 1510: putstatic 114
     [java] 1513: const 122
     [java] 1518: putstatic 115
     [java] 1521: const 105
     [java] 1526: putstatic 116
     [java] 1529: const 110
     [java] 1534: putstatic 117
     [java] 1537: const 117
     [java] 1542: putstatic 118
     [java] 1545: const_m1
     [java] 1546: putstatic 119
     [java] 1549: const 238
     [java] 1554: putstatic 120
     [java] 1557: const 112
     [java] 1562: putstatic 121
     [java] 1565: const 111
     [java] 1570: putstatic 122
     [java] 1573: const 115
     [java] 1578: putstatic 123
     [java] 1581: const 116
     [java] 1586: putstatic 124
     [java] 1589: const 97
     [java] 1594: putstatic 125
     [java] 1597: const 118
     [java] 1602: putstatic 126
     [java] 1605: const 105
     [java] 1610: putstatic 127
     [java] 1613: const 80
     [java] 1618: putstatic 128
     [java] 1621: const 111
     [java] 1626: putstatic 129
     [java] 1629: const 108
     [java] 1634: putstatic 130
     [java] 1637: const 117
     [java] 1642: putstatic 131
     [java] 1645: const 112
     [java] 1650: putstatic 132
     [java] 1653: const 114
     [java] 1658: putstatic 133
     [java] 1661: const 101
     [java] 1666: putstatic 134
     [java] 1669: const 99
     [java] 1674: putstatic 135
     [java] 1677: const 110
     [java] 1682: putstatic 136
     [java] 1685: const 105
     [java] 1690: putstatic 137
     [java] 1693: const 107
     [java] 1698: putstatic 138
     [java] 1701: const_m1
     [java] 1702: putstatic 139
     [java] 1705: const 248
     [java] 1710: putstatic 140
     [java] 1713: const 122
     [java] 1718: putstatic 141
     [java] 1721: const 97
     [java] 1726: putstatic 142
     [java] 1729: const 112
     [java] 1734: putstatic 143
     [java] 1737: const 114
     [java] 1742: putstatic 144
     [java] 1745: const 101
     [java] 1750: putstatic 145
     [java] 1753: const 109
     [java] 1758: putstatic 146
     [java] 1761: const 105
     [java] 1766: putstatic 147
     [java] 1769: const 110
     [java] 1774: putstatic 148
     [java] 1777: const 97
     [java] 1782: putstatic 149
     [java] 1785: const_m1
     [java] 1786: putstatic 150
     [java] 1789: const 321
     [java] 1794: putstatic 151
     [java] 1797: const 104
     [java] 1802: putstatic 152
     [java] 1805: const 105
     [java] 1810: putstatic 153
     [java] 1813: const 84
     [java] 1818: putstatic 154
     [java] 1821: const 104
     [java] 1826: putstatic 155
     [java] 1829: const 105
     [java] 1834: putstatic 156
     [java] 1837: const 115
     [java] 1842: putstatic 157
     [java] 1845: const_m1
     [java] 1846: putstatic 158
     [java] 1849: const 51
     [java] 1854: putstatic 159
     [java] 1857: const 117
     [java] 1862: putstatic 160
     [java] 1865: const 99
     [java] 1870: putstatic 161
     [java] 1873: const 105
     [java] 1878: putstatic 162
     [java] 1881: const 116
     [java] 1886: putstatic 163
     [java] 1889: const 97
     [java] 1894: putstatic 164
     [java] 1897: const 106
     [java] 1902: putstatic 165
     [java] 1905: const 84
     [java] 1910: putstatic 166
     [java] 1913: const 101
     [java] 1918: putstatic 167
     [java] 1921: const 122
     [java] 1926: putstatic 168
     [java] 1929: const 105
     [java] 1934: putstatic 169
     [java] 1937: const 110
     [java] 1942: putstatic 170
     [java] 1945: const 117
     [java] 1950: putstatic 171
     [java] 1953: const_m1
     [java] 1954: putstatic 172
     [java] 1957: const 84
     [java] 1962: putstatic 173
     [java] 1965: const 81
     [java] 1970: putstatic 174
     [java] 1973: const_m1
     [java] 1974: putstatic 175
     [java] 1977: const 102
     [java] 1982: putstatic 176
     [java] 1985: const 112
     [java] 1990: putstatic 177
     [java] 1993: const 111
     [java] 1998: putstatic 178
     [java] 2001: const 115
     [java] 2006: putstatic 179
     [java] 2009: const 116
     [java] 2014: putstatic 180
     [java] 2017: const 97
     [java] 2022: putstatic 181
     [java] 2025: const 118
     [java] 2030: putstatic 182
     [java] 2033: const 105
     [java] 2038: putstatic 183
     [java] 2041: const 86
     [java] 2046: putstatic 184
     [java] 2049: const 114
     [java] 2054: putstatic 185
     [java] 2057: const 115
     [java] 2062: putstatic 186
     [java] 2065: const 116
     [java] 2070: putstatic 187
     [java] 2073: const 117
     [java] 2078: putstatic 188
     [java] 2081: const_m1
     [java] 2082: putstatic 189
     [java] 2085: const 160
     [java] 2090: putstatic 190
     [java] 2093: const 100
     [java] 2098: putstatic 191
     [java] 2101: const 111
     [java] 2106: putstatic 192
     [java] 2109: const 104
     [java] 2114: putstatic 193
     [java] 2117: const 118
     [java] 2122: putstatic 194
     [java] 2125: const 86
     [java] 2130: putstatic 195
     [java] 2133: const 114
     [java] 2138: putstatic 196
     [java] 2141: const 115
     [java] 2146: putstatic 197
     [java] 2149: const 116
     [java] 2154: putstatic 198
     [java] 2157: const 117
     [java] 2162: putstatic 199
     [java] 2165: const_m1
     [java] 2166: putstatic 200
     [java] 2169: const 170
     [java] 2174: putstatic 201
     [java] 2177: const 100
     [java] 2182: putstatic 202
     [java] 2185: const 111
     [java] 2190: putstatic 203
     [java] 2193: const 104
     [java] 2198: putstatic 204
     [java] 2201: const 118
     [java] 2206: putstatic 205
     [java] 2209: const 84
     [java] 2214: putstatic 206
     [java] 2217: const 101
     [java] 2222: putstatic 207
     [java] 2225: const 122
     [java] 2230: putstatic 208
     [java] 2233: const 105
     [java] 2238: putstatic 209
     [java] 2241: const 110
     [java] 2246: putstatic 210
     [java] 2249: const 117
     [java] 2254: putstatic 211
     [java] 2257: const_m1
     [java] 2258: putstatic 212
     [java] 2261: const 181
     [java] 2266: putstatic 213
     [java] 2269: const 104
     [java] 2274: putstatic 214
     [java] 2277: const 105
     [java] 2282: putstatic 215
     [java] 2285: const 114
     [java] 2290: putstatic 216
     [java] 2293: const_m1
     [java] 2294: putstatic 217
     [java] 2297: const 192
     [java] 2302: putstatic 218
     [java] 2305: const -2
     [java] 2310: putstatic 219
     [java] 2313: const 104
     [java] 2318: putstatic 220
     [java] 2321: const 105
     [java] 2326: putstatic 221
     [java] 2329: const_m1
     [java] 2330: putstatic 222
     [java] 2333: const 338
     [java] 2338: putstatic 223
     [java] 2341: const 112
     [java] 2346: putstatic 224
     [java] 2349: const 111
     [java] 2354: putstatic 225
     [java] 2357: const 115
     [java] 2362: putstatic 226
     [java] 2365: const 116
     [java] 2370: putstatic 227
     [java] 2373: const 97
     [java] 2378: putstatic 228
     [java] 2381: const 118
     [java] 2386: putstatic 229
     [java] 2389: const 105
     [java] 2394: putstatic 230
     [java] 2397: const 84
     [java] 2402: putstatic 231
     [java] 2405: const 101
     [java] 2410: putstatic 232
     [java] 2413: const 122
     [java] 2418: putstatic 233
     [java] 2421: const 105
     [java] 2426: putstatic 234
     [java] 2429: const 110
     [java] 2434: putstatic 235
     [java] 2437: const 117
     [java] 2442: putstatic 236
     [java] 2445: const_m1
     [java] 2446: putstatic 237
     [java] 2449: const 364
     [java] 2454: putstatic 238
     [java] 2457: const 112
     [java] 2462: putstatic 239
     [java] 2465: const 111
     [java] 2470: putstatic 240
     [java] 2473: const 115
     [java] 2478: putstatic 241
     [java] 2481: const 116
     [java] 2486: putstatic 242
     [java] 2489: const 97
     [java] 2494: putstatic 243
     [java] 2497: const 118
     [java] 2502: putstatic 244
     [java] 2505: const 105
     [java] 2510: putstatic 245
     [java] 2513: const 83
     [java] 2518: putstatic 246
     [java] 2521: const 116
     [java] 2526: putstatic 247
     [java] 2529: const 114
     [java] 2534: putstatic 248
     [java] 2537: const 97
     [java] 2542: putstatic 249
     [java] 2545: const 110
     [java] 2550: putstatic 250
     [java] 2553: const 105
     [java] 2558: putstatic 251
     [java] 2561: const 99
     [java] 2566: putstatic 252
     [java] 2569: const 101
     [java] 2574: putstatic 253
     [java] 2577: const_m1
     [java] 2578: putstatic 254
     [java] 2581: const 374
     [java] 2586: putstatic 255
     [java] 2589: const 122
     [java] 2594: putstatic 256
     [java] 2597: const 97
     [java] 2602: putstatic 257
     [java] 2605: const 112
     [java] 2610: putstatic 258
     [java] 2613: const 114
     [java] 2618: putstatic 259
     [java] 2621: const 101
     [java] 2626: putstatic 260
     [java] 2629: const 109
     [java] 2634: putstatic 261
     [java] 2637: const 105
     [java] 2642: putstatic 262
     [java] 2645: const 110
     [java] 2650: putstatic 263
     [java] 2653: const 97
     [java] 2658: putstatic 264
     [java] 2661: const_m1
     [java] 2662: putstatic 265
     [java] 2665: const 403
     [java] 2670: putstatic 266
     [java] 2673: const 104
     [java] 2678: putstatic 267
     [java] 2681: const 105
     [java] 2686: putstatic 268
     [java] 2689: const 114
     [java] 2694: putstatic 269
     [java] 2697: const_m1
     [java] 2698: putstatic 270
     [java] 2701: const 426
     [java] 2706: putstatic 271
     [java] 2709: const 104
     [java] 2714: putstatic 272
     [java] 2717: const 105
     [java] 2722: putstatic 273
     [java] 2725: const 84
     [java] 2730: putstatic 274
     [java] 2733: const 104
     [java] 2738: putstatic 275
     [java] 2741: const 105
     [java] 2746: putstatic 276
     [java] 2749: const 115
     [java] 2754: putstatic 277
     [java] 2757: const_m1
     [java] 2758: putstatic 278
     [java] 2761: const 51
     [java] 2766: putstatic 279
     [java] 2769: const 117
     [java] 2774: putstatic 280
     [java] 2777: const 99
     [java] 2782: putstatic 281
     [java] 2785: const 105
     [java] 2790: putstatic 282
     [java] 2793: const 116
     [java] 2798: putstatic 283
     [java] 2801: const 97
     [java] 2806: putstatic 284
     [java] 2809: const 106
     [java] 2814: putstatic 285
     [java] 2817: const 84
     [java] 2822: putstatic 286
     [java] 2825: const 101
     [java] 2830: putstatic 287
     [java] 2833: const 122
     [java] 2838: putstatic 288
     [java] 2841: const 105
     [java] 2846: putstatic 289
     [java] 2849: const 110
     [java] 2854: putstatic 290
     [java] 2857: const 117
     [java] 2862: putstatic 291
     [java] 2865: const_m1
     [java] 2866: putstatic 292
     [java] 2869: const 84
     [java] 2874: putstatic 293
     [java] 2877: const 81
     [java] 2882: putstatic 294
     [java] 2885: const_m1
     [java] 2886: putstatic 295
     [java] 2889: const 102
     [java] 2894: putstatic 296
     [java] 2897: const 112
     [java] 2902: putstatic 297
     [java] 2905: const 111
     [java] 2910: putstatic 298
     [java] 2913: const 115
     [java] 2918: putstatic 299
     [java] 2921: const 116
     [java] 2926: putstatic 300
     [java] 2929: const 97
     [java] 2934: putstatic 301
     [java] 2937: const 118
     [java] 2942: putstatic 302
     [java] 2945: const 105
     [java] 2950: putstatic 303
     [java] 2953: const 86
     [java] 2958: putstatic 304
     [java] 2961: const 114
     [java] 2966: putstatic 305
     [java] 2969: const 115
     [java] 2974: putstatic 306
     [java] 2977: const 116
     [java] 2982: putstatic 307
     [java] 2985: const 117
     [java] 2990: putstatic 308
     [java] 2993: const_m1
     [java] 2994: putstatic 309
     [java] 2997: const 160
     [java] 3002: putstatic 310
     [java] 3005: const 100
     [java] 3010: putstatic 311
     [java] 3013: const 111
     [java] 3018: putstatic 312
     [java] 3021: const 104
     [java] 3026: putstatic 313
     [java] 3029: const 118
     [java] 3034: putstatic 314
     [java] 3037: const 86
     [java] 3042: putstatic 315
     [java] 3045: const 114
     [java] 3050: putstatic 316
     [java] 3053: const 115
     [java] 3058: putstatic 317
     [java] 3061: const 116
     [java] 3066: putstatic 318
     [java] 3069: const 117
     [java] 3074: putstatic 319
     [java] 3077: const_m1
     [java] 3078: putstatic 320
     [java] 3081: const 170
     [java] 3086: putstatic 321
     [java] 3089: const 100
     [java] 3094: putstatic 322
     [java] 3097: const 111
     [java] 3102: putstatic 323
     [java] 3105: const 104
     [java] 3110: putstatic 324
     [java] 3113: const 118
     [java] 3118: putstatic 325
     [java] 3121: const 84
     [java] 3126: putstatic 326
     [java] 3129: const 101
     [java] 3134: putstatic 327
     [java] 3137: const 122
     [java] 3142: putstatic 328
     [java] 3145: const 105
     [java] 3150: putstatic 329
     [java] 3153: const 110
     [java] 3158: putstatic 330
     [java] 3161: const 117
     [java] 3166: putstatic 331
     [java] 3169: const_m1
     [java] 3170: putstatic 332
     [java] 3173: const 181
     [java] 3178: putstatic 333
     [java] 3181: const -2
     [java] 3186: putstatic 334
     [java] 3189: enter 0 9
     [java] 3192: const 6
     [java] 3197: newarray 1
     [java] 3199: store_0
     [java] 3200: new 24
     [java] 3203: dup
     [java] 3204: const 102
     [java] 3209: putfield 0
     [java] 3212: store_2
     [java] 3213: new 24
     [java] 3216: dup
     [java] 3217: const 102
     [java] 3222: putfield 0
     [java] 3225: store_3
     [java] 3226: new 24
     [java] 3229: dup
     [java] 3230: const 102
     [java] 3235: putfield 0
     [java] 3238: store 4
     [java] 3240: new 32
     [java] 3243: dup
     [java] 3244: const 220
     [java] 3249: putfield 0
     [java] 3252: store 5
     [java] 3254: new 32
     [java] 3257: dup
     [java] 3258: const 220
     [java] 3263: putfield 0
     [java] 3266: store 6
     [java] 3268: new 32
     [java] 3271: dup
     [java] 3272: const 220
     [java] 3277: putfield 0
     [java] 3280: store 7
     [java] 3282: load_2
     [java] 3283: const_1
     [java] 3284: load_2
     [java] 3285: getfield 0
     [java] 3288: invokevirtual postaviPoluprecnik
     [java] 3365: load_3
     [java] 3366: const_2
     [java] 3367: load_3
     [java] 3368: getfield 0
     [java] 3371: invokevirtual postaviPoluprecnik
     [java] 3448: load 4
     [java] 3450: const_3
     [java] 3451: load 4
     [java] 3453: getfield 0
     [java] 3456: invokevirtual postaviPoluprecnik
     [java] 3533: load 5
     [java] 3535: const_1
     [java] 3536: const_2
     [java] 3537: const_3
     [java] 3538: load 5
     [java] 3540: getfield 0
     [java] 3543: invokevirtual postaviStranice
     [java] 3608: load 6
     [java] 3610: const_2
     [java] 3611: const_3
     [java] 3612: const_4
     [java] 3613: load 6
     [java] 3615: getfield 0
     [java] 3618: invokevirtual postaviStranice
     [java] 3683: load 7
     [java] 3685: const_3
     [java] 3686: const_4
     [java] 3687: const_5
     [java] 3688: load 7
     [java] 3690: getfield 0
     [java] 3693: invokevirtual postaviStranice
     [java] 3758: load_0
     [java] 3759: const_0
     [java] 3760: load_2
     [java] 3761: astore
     [java] 3762: load_0
     [java] 3763: const_2
     [java] 3764: load_3
     [java] 3765: astore
     [java] 3766: load_0
     [java] 3767: const_4
     [java] 3768: load 4
     [java] 3770: astore
     [java] 3771: load_0
     [java] 3772: const_1
     [java] 3773: load 5
     [java] 3775: astore
     [java] 3776: load_0
     [java] 3777: const_3
     [java] 3778: load 6
     [java] 3780: astore
     [java] 3781: load_0
     [java] 3782: const_5
     [java] 3783: load 7
     [java] 3785: astore
     [java] 3786: load 5
     [java] 3788: new 20
     [java] 3791: dup
     [java] 3792: const_4
     [java] 3793: putfield 0
     [java] 3796: load 5
     [java] 3798: getfield 0
     [java] 3801: invokevirtual hir
     [java] 3818: load 5
     [java] 3820: new 24
     [java] 3823: dup
     [java] 3824: const 102
     [java] 3829: putfield 0
     [java] 3832: load 5
     [java] 3834: getfield 0
     [java] 3837: invokevirtual hir
     [java] 3854: load 5
     [java] 3856: new 32
     [java] 3859: dup
     [java] 3860: const 220
     [java] 3865: putfield 0
     [java] 3868: load 5
     [java] 3870: getfield 0
     [java] 3873: invokevirtual hir
     [java] 3890: read
     [java] 3891: store 8
     [java] 3893: const_0
     [java] 3894: store_1
     [java] 3895: load_0
     [java] 3896: load_1
     [java] 3897: aload
     [java] 3898: load 8
     [java] 3900: load_0
     [java] 3901: load_1
     [java] 3902: aload
     [java] 3903: getfield 0
     [java] 3906: invokevirtual postaviTezinu
     [java] 3963: load_1
     [java] 3964: pop
     [java] 3965: inc 1,1
     [java] 3968: load_1
     [java] 3969: const 6
     [java] 3974: jlt -79 (=3895)
     [java] 3977: const_0
     [java] 3978: putstatic 1
     [java] 3981: const_0
     [java] 3982: putstatic 3
     [java] 3985: const_1
     [java] 3986: store_1
     [java] 3987: load_1
     [java] 3988: const_2
     [java] 3989: rem
     [java] 3990: const_0
     [java] 3991: jne 11 (=4002)
     [java] 3994: load_1
     [java] 3995: pop
     [java] 3996: inc 1,1
     [java] 3999: jmp 106 (=4105)
     [java] 4002: getstatic 1
     [java] 4005: load_0
     [java] 4006: load_1
     [java] 4007: const_1
     [java] 4008: sub
     [java] 4009: aload
     [java] 4010: load_0
     [java] 4011: load_1
     [java] 4012: const_1
     [java] 4013: sub
     [java] 4014: aload
     [java] 4015: getfield 0
     [java] 4018: invokevirtual zapremina
     [java] 4059: add
     [java] 4060: putstatic 1
     [java] 4063: getstatic 3
     [java] 4066: load_0
     [java] 4067: load_1
     [java] 4068: const_1
     [java] 4069: sub
     [java] 4070: aload
     [java] 4071: load_0
     [java] 4072: load_1
     [java] 4073: const_1
     [java] 4074: sub
     [java] 4075: aload
     [java] 4076: getfield 0
     [java] 4079: invokevirtual Q
     [java] 4088: add
     [java] 4089: putstatic 3
     [java] 4092: load_0
     [java] 4093: load_1
     [java] 4094: const_1
     [java] 4095: sub
     [java] 4096: aload
     [java] 4097: call -3617 (=480)
     [java] 4100: load_1
     [java] 4101: pop
     [java] 4102: inc 1,1
     [java] 4105: load_1
     [java] 4106: const 6
     [java] 4111: jle -124 (=3987)
     [java] 4114: const_0
     [java] 4115: putstatic 0
     [java] 4118: const_0
     [java] 4119: putstatic 2
     [java] 4122: const_1
     [java] 4123: store_1
     [java] 4124: load_1
     [java] 4125: const_2
     [java] 4126: rem
     [java] 4127: const_1
     [java] 4128: jne 11 (=4139)
     [java] 4131: load_1
     [java] 4132: pop
     [java] 4133: inc 1,1
     [java] 4136: jmp 106 (=4242)
     [java] 4139: getstatic 0
     [java] 4142: load_0
     [java] 4143: load_1
     [java] 4144: const_1
     [java] 4145: sub
     [java] 4146: aload
     [java] 4147: load_0
     [java] 4148: load_1
     [java] 4149: const_1
     [java] 4150: sub
     [java] 4151: aload
     [java] 4152: getfield 0
     [java] 4155: invokevirtual zapremina
     [java] 4196: add
     [java] 4197: putstatic 0
     [java] 4200: getstatic 2
     [java] 4203: load_0
     [java] 4204: load_1
     [java] 4205: const_1
     [java] 4206: sub
     [java] 4207: aload
     [java] 4208: load_0
     [java] 4209: load_1
     [java] 4210: const_1
     [java] 4211: sub
     [java] 4212: aload
     [java] 4213: getfield 0
     [java] 4216: invokevirtual Q
     [java] 4225: add
     [java] 4226: putstatic 2
     [java] 4229: load_0
     [java] 4230: load_1
     [java] 4231: const_1
     [java] 4232: sub
     [java] 4233: aload
     [java] 4234: call -3754 (=480)
     [java] 4237: load_1
     [java] 4238: pop
     [java] 4239: inc 1,1
     [java] 4242: load_1
     [java] 4243: const 6
     [java] 4248: jle -124 (=4124)
     [java] 4251: getstatic 1
     [java] 4254: const_5
     [java] 4255: print
     [java] 4256: const 10
     [java] 4261: const_1
     [java] 4262: bprint
     [java] 4263: getstatic 0
     [java] 4266: const_5
     [java] 4267: print
     [java] 4268: const 10
     [java] 4273: const_1
     [java] 4274: bprint
     [java] 4275: getstatic 3
     [java] 4278: const_5
     [java] 4279: print
     [java] 4280: const 10
     [java] 4285: const_1
     [java] 4286: bprint
     [java] 4287: getstatic 2
     [java] 4290: const_5
     [java] 4291: print
     [java] 4292: const 10
     [java] 4297: const_1
     [java] 4298: bprint
     [java] 4299: const_0
     [java] 4300: store_1
     [java] 4301: load_1
     [java] 4302: const_1
     [java] 4303: add
     [java] 4304: dup
     [java] 4305: const_1
     [java] 4306: jeq 40 (=4346)
     [java] 4309: dup
     [java] 4310: const_3
     [java] 4311: jeq 41 (=4352)
     [java] 4314: dup
     [java] 4315: const_2
     [java] 4316: jeq 39 (=4355)
     [java] 4319: dup
     [java] 4320: const_5
     [java] 4321: jeq 40 (=4361)
     [java] 4324: dup
     [java] 4325: const 6
     [java] 4330: jeq 41 (=4371)
     [java] 4333: dup
     [java] 4334: const 9
     [java] 4339: jeq 39 (=4378)
     [java] 4342: pop
     [java] 4343: jmp 42 (=4385)
     [java] 4346: const_1
     [java] 4347: const_5
     [java] 4348: print
     [java] 4349: jmp 36 (=4385)
     [java] 4352: const_3
     [java] 4353: const_5
     [java] 4354: print
     [java] 4355: const_2
     [java] 4356: const_5
     [java] 4357: print
     [java] 4358: jmp 27 (=4385)
     [java] 4361: const_5
     [java] 4362: const_5
     [java] 4363: print
     [java] 4364: load_1
     [java] 4365: const_2
     [java] 4366: add
     [java] 4367: store_1
     [java] 4368: jmp 29 (=4397)
     [java] 4371: const 6
     [java] 4376: const_5
     [java] 4377: print
     [java] 4378: const 9
     [java] 4383: const_5
     [java] 4384: print
     [java] 4385: const 10
     [java] 4390: const_1
     [java] 4391: bprint
     [java] 4392: load_1
     [java] 4393: pop
     [java] 4394: inc 1,1
     [java] 4397: load_1
     [java] 4398: const 10
     [java] 4403: jlt -102 (=4301)
     [java] 4406: load_0
     [java] 4407: const_0
     [java] 4408: const_0
     [java] 4409: astore
     [java] 4410: load_0
     [java] 4411: const_0
     [java] 4412: aload
     [java] 4413: const_0
     [java] 4414: jne 10 (=4424)
     [java] 4417: const 69
     [java] 4422: const_1
     [java] 4423: bprint
     [java] 4424: new 20
     [java] 4427: dup
     [java] 4428: const_4
     [java] 4429: putfield 0
     [java] 4432: const_0
     [java] 4433: jne 13 (=4446)
     [java] 4436: const 80
     [java] 4441: const_1
     [java] 4442: bprint
     [java] 4443: jmp 10 (=4453)
     [java] 4446: const 75
     [java] 4451: const_1
     [java] 4452: bprint
     [java] 4453: const_0
     [java] 4454: store_0
     [java] 4455: load_0
     [java] 4456: const_0
     [java] 4457: jne 10 (=4467)
     [java] 4460: const 78
     [java] 4465: const_1
     [java] 4466: bprint
     [java] 4467: const_0
     [java] 4468: const_2
     [java] 4469: newarray 1
     [java] 4471: jne 10 (=4481)
     [java] 4474: const 87
     [java] 4479: const_1
     [java] 4480: bprint
     [java] 4481: exit
     [java] 4482: return

runObj:
     [java] 
     [java]   pos: instruction operands
     [java]      | expressionstack
     [java] -----------------------------
     [java]   669: const       104 
     [java]      | 104 
     [java]   674: putstatic   4 
     [java]      | 
     [java]   677: const       105 
     [java]      | 105 
     [java]   682: putstatic   5 
     [java]      | 
     [java]   685: const_m1    
     [java]      | -1 
     [java]   686: putstatic   6 
     [java]      | 
     [java]   689: const       25 
     [java]      | 25 
     [java]   694: putstatic   7 
     [java]      | 
     [java]   697: const       104 
     [java]      | 104 
     [java]   702: putstatic   8 
     [java]      | 
     [java]   705: const       105 
     [java]      | 105 
     [java]   710: putstatic   9 
     [java]      | 
     [java]   713: const       84 
     [java]      | 84 
     [java]   718: putstatic   10 
     [java]      | 
     [java]   721: const       104 
     [java]      | 104 
     [java]   726: putstatic   11 
     [java]      | 
     [java]   729: const       105 
     [java]      | 105 
     [java]   734: putstatic   12 
     [java]      | 
     [java]   737: const       115 
     [java]      | 115 
     [java]   742: putstatic   13 
     [java]      | 
     [java]   745: const_m1    
     [java]      | -1 
     [java]   746: putstatic   14 
     [java]      | 
     [java]   749: const       51 
     [java]      | 51 
     [java]   754: putstatic   15 
     [java]      | 
     [java]   757: const       112 
     [java]      | 112 
     [java]   762: putstatic   16 
     [java]      | 
     [java]   765: const       111 
     [java]      | 111 
     [java]   770: putstatic   17 
     [java]      | 
     [java]   773: const       115 
     [java]      | 115 
     [java]   778: putstatic   18 
     [java]      | 
     [java]   781: const       116 
     [java]      | 116 
     [java]   786: putstatic   19 
     [java]      | 
     [java]   789: const       97 
     [java]      | 97 
     [java]   794: putstatic   20 
     [java]      | 
     [java]   797: const       118 
     [java]      | 118 
     [java]   802: putstatic   21 
     [java]      | 
     [java]   805: const       105 
     [java]      | 105 
     [java]   810: putstatic   22 
     [java]      | 
     [java]   813: const       84 
     [java]      | 84 
     [java]   818: putstatic   23 
     [java]      | 
     [java]   821: const       101 
     [java]      | 101 
     [java]   826: putstatic   24 
     [java]      | 
     [java]   829: const       122 
     [java]      | 122 
     [java]   834: putstatic   25 
     [java]      | 
     [java]   837: const       105 
     [java]      | 105 
     [java]   842: putstatic   26 
     [java]      | 
     [java]   845: const       110 
     [java]      | 110 
     [java]   850: putstatic   27 
     [java]      | 
     [java]   853: const       117 
     [java]      | 117 
     [java]   858: putstatic   28 
     [java]      | 
     [java]   861: const_m1    
     [java]      | -1 
     [java]   862: putstatic   29 
     [java]      | 
     [java]   865: const       74 
     [java]      | 74 
     [java]   870: putstatic   30 
     [java]      | 
     [java]   873: const       117 
     [java]      | 117 
     [java]   878: putstatic   31 
     [java]      | 
     [java]   881: const       99 
     [java]      | 99 
     [java]   886: putstatic   32 
     [java]      | 
     [java]   889: const       105 
     [java]      | 105 
     [java]   894: putstatic   33 
     [java]      | 
     [java]   897: const       116 
     [java]      | 116 
     [java]   902: putstatic   34 
     [java]      | 
     [java]   905: const       97 
     [java]      | 97 
     [java]   910: putstatic   35 
     [java]      | 
     [java]   913: const       106 
     [java]      | 106 
     [java]   918: putstatic   36 
     [java]      | 
     [java]   921: const       84 
     [java]      | 84 
     [java]   926: putstatic   37 
     [java]      | 
     [java]   929: const       101 
     [java]      | 101 
     [java]   934: putstatic   38 
     [java]      | 
     [java]   937: const       122 
     [java]      | 122 
     [java]   942: putstatic   39 
     [java]      | 
     [java]   945: const       105 
     [java]      | 105 
     [java]   950: putstatic   40 
     [java]      | 
     [java]   953: const       110 
     [java]      | 110 
     [java]   958: putstatic   41 
     [java]      | 
     [java]   961: const       117 
     [java]      | 117 
     [java]   966: putstatic   42 
     [java]      | 
     [java]   969: const_m1    
     [java]      | -1 
     [java]   970: putstatic   43 
     [java]      | 
     [java]   973: const       84 
     [java]      | 84 
     [java]   978: putstatic   44 
     [java]      | 
     [java]   981: const       122 
     [java]      | 122 
     [java]   986: putstatic   45 
     [java]      | 
     [java]   989: const       97 
     [java]      | 97 
     [java]   994: putstatic   46 
     [java]      | 
     [java]   997: const       112 
     [java]      | 112 
     [java]  1002: putstatic   47 
     [java]      | 
     [java]  1005: const       114 
     [java]      | 114 
     [java]  1010: putstatic   48 
     [java]      | 
     [java]  1013: const       101 
     [java]      | 101 
     [java]  1018: putstatic   49 
     [java]      | 
     [java]  1021: const       109 
     [java]      | 109 
     [java]  1026: putstatic   50 
     [java]      | 
     [java]  1029: const       105 
     [java]      | 105 
     [java]  1034: putstatic   51 
     [java]      | 
     [java]  1037: const       110 
     [java]      | 110 
     [java]  1042: putstatic   52 
     [java]      | 
     [java]  1045: const       97 
     [java]      | 97 
     [java]  1050: putstatic   53 
     [java]      | 
     [java]  1053: const_m1    
     [java]      | -1 
     [java]  1054: putstatic   54 
     [java]      | 
     [java]  1057: const       94 
     [java]      | 94 
     [java]  1062: putstatic   55 
     [java]      | 
     [java]  1065: const       81 
     [java]      | 81 
     [java]  1070: putstatic   56 
     [java]      | 
     [java]  1073: const_m1    
     [java]      | -1 
     [java]  1074: putstatic   57 
     [java]      | 
     [java]  1077: const       102 
     [java]      | 102 
     [java]  1082: putstatic   58 
     [java]      | 
     [java]  1085: const       112 
     [java]      | 112 
     [java]  1090: putstatic   59 
     [java]      | 
     [java]  1093: const       111 
     [java]      | 111 
     [java]  1098: putstatic   60 
     [java]      | 
     [java]  1101: const       115 
     [java]      | 115 
     [java]  1106: putstatic   61 
     [java]      | 
     [java]  1109: const       116 
     [java]      | 116 
     [java]  1114: putstatic   62 
     [java]      | 
     [java]  1117: const       97 
     [java]      | 97 
     [java]  1122: putstatic   63 
     [java]      | 
     [java]  1125: const       118 
     [java]      | 118 
     [java]  1130: putstatic   64 
     [java]      | 
     [java]  1133: const       105 
     [java]      | 105 
     [java]  1138: putstatic   65 
     [java]      | 
     [java]  1141: const       86 
     [java]      | 86 
     [java]  1146: putstatic   66 
     [java]      | 
     [java]  1149: const       114 
     [java]      | 114 
     [java]  1154: putstatic   67 
     [java]      | 
     [java]  1157: const       115 
     [java]      | 115 
     [java]  1162: putstatic   68 
     [java]      | 
     [java]  1165: const       116 
     [java]      | 116 
     [java]  1170: putstatic   69 
     [java]      | 
     [java]  1173: const       117 
     [java]      | 117 
     [java]  1178: putstatic   70 
     [java]      | 
     [java]  1181: const_m1    
     [java]      | -1 
     [java]  1182: putstatic   71 
     [java]      | 
     [java]  1185: const       160 
     [java]      | 160 
     [java]  1190: putstatic   72 
     [java]      | 
     [java]  1193: const       100 
     [java]      | 100 
     [java]  1198: putstatic   73 
     [java]      | 
     [java]  1201: const       111 
     [java]      | 111 
     [java]  1206: putstatic   74 
     [java]      | 
     [java]  1209: const       104 
     [java]      | 104 
     [java]  1214: putstatic   75 
     [java]      | 
     [java]  1217: const       118 
     [java]      | 118 
     [java]  1222: putstatic   76 
     [java]      | 
     [java]  1225: const       86 
     [java]      | 86 
     [java]  1230: putstatic   77 
     [java]      | 
     [java]  1233: const       114 
     [java]      | 114 
     [java]  1238: putstatic   78 
     [java]      | 
     [java]  1241: const       115 
     [java]      | 115 
     [java]  1246: putstatic   79 
     [java]      | 
     [java]  1249: const       116 
     [java]      | 116 
     [java]  1254: putstatic   80 
     [java]      | 
     [java]  1257: const       117 
     [java]      | 117 
     [java]  1262: putstatic   81 
     [java]      | 
     [java]  1265: const_m1    
     [java]      | -1 
     [java]  1266: putstatic   82 
     [java]      | 
     [java]  1269: const       170 
     [java]      | 170 
     [java]  1274: putstatic   83 
     [java]      | 
     [java]  1277: const       100 
     [java]      | 100 
     [java]  1282: putstatic   84 
     [java]      | 
     [java]  1285: const       111 
     [java]      | 111 
     [java]  1290: putstatic   85 
     [java]      | 
     [java]  1293: const       104 
     [java]      | 104 
     [java]  1298: putstatic   86 
     [java]      | 
     [java]  1301: const       118 
     [java]      | 118 
     [java]  1306: putstatic   87 
     [java]      | 
     [java]  1309: const       84 
     [java]      | 84 
     [java]  1314: putstatic   88 
     [java]      | 
     [java]  1317: const       101 
     [java]      | 101 
     [java]  1322: putstatic   89 
     [java]      | 
     [java]  1325: const       122 
     [java]      | 122 
     [java]  1330: putstatic   90 
     [java]      | 
     [java]  1333: const       105 
     [java]      | 105 
     [java]  1338: putstatic   91 
     [java]      | 
     [java]  1341: const       110 
     [java]      | 110 
     [java]  1346: putstatic   92 
     [java]      | 
     [java]  1349: const       117 
     [java]      | 117 
     [java]  1354: putstatic   93 
     [java]      | 
     [java]  1357: const_m1    
     [java]      | -1 
     [java]  1358: putstatic   94 
     [java]      | 
     [java]  1361: const       181 
     [java]      | 181 
     [java]  1366: putstatic   95 
     [java]      | 
     [java]  1369: const       104 
     [java]      | 104 
     [java]  1374: putstatic   96 
     [java]      | 
     [java]  1377: const       105 
     [java]      | 105 
     [java]  1382: putstatic   97 
     [java]      | 
     [java]  1385: const       114 
     [java]      | 114 
     [java]  1390: putstatic   98 
     [java]      | 
     [java]  1393: const_m1    
     [java]      | -1 
     [java]  1394: putstatic   99 
     [java]      | 
     [java]  1397: const       192 
     [java]      | 192 
     [java]  1402: putstatic   100 
     [java]      | 
     [java]  1405: const       -2 
     [java]      | -2 
     [java]  1410: putstatic   101 
     [java]      | 
     [java]  1413: const       104 
     [java]      | 104 
     [java]  1418: putstatic   102 
     [java]      | 
     [java]  1421: const       105 
     [java]      | 105 
     [java]  1426: putstatic   103 
     [java]      | 
     [java]  1429: const_m1    
     [java]      | -1 
     [java]  1430: putstatic   104 
     [java]      | 
     [java]  1433: const       212 
     [java]      | 212 
     [java]  1438: putstatic   105 
     [java]      | 
     [java]  1441: const       112 
     [java]      | 112 
     [java]  1446: putstatic   106 
     [java]      | 
     [java]  1449: const       111 
     [java]      | 111 
     [java]  1454: putstatic   107 
     [java]      | 
     [java]  1457: const       115 
     [java]      | 115 
     [java]  1462: putstatic   108 
     [java]      | 
     [java]  1465: const       116 
     [java]      | 116 
     [java]  1470: putstatic   109 
     [java]      | 
     [java]  1473: const       97 
     [java]      | 97 
     [java]  1478: putstatic   110 
     [java]      | 
     [java]  1481: const       118 
     [java]      | 118 
     [java]  1486: putstatic   111 
     [java]      | 
     [java]  1489: const       105 
     [java]      | 105 
     [java]  1494: putstatic   112 
     [java]      | 
     [java]  1497: const       84 
     [java]      | 84 
     [java]  1502: putstatic   113 
     [java]      | 
     [java]  1505: const       101 
     [java]      | 101 
     [java]  1510: putstatic   114 
     [java]      | 
     [java]  1513: const       122 
     [java]      | 122 
     [java]  1518: putstatic   115 
     [java]      | 
     [java]  1521: const       105 
     [java]      | 105 
     [java]  1526: putstatic   116 
     [java]      | 
     [java]  1529: const       110 
     [java]      | 110 
     [java]  1534: putstatic   117 
     [java]      | 
     [java]  1537: const       117 
     [java]      | 117 
     [java]  1542: putstatic   118 
     [java]      | 
     [java]  1545: const_m1    
     [java]      | -1 
     [java]  1546: putstatic   119 
     [java]      | 
     [java]  1549: const       238 
     [java]      | 238 
     [java]  1554: putstatic   120 
     [java]      | 
     [java]  1557: const       112 
     [java]      | 112 
     [java]  1562: putstatic   121 
     [java]      | 
     [java]  1565: const       111 
     [java]      | 111 
     [java]  1570: putstatic   122 
     [java]      | 
     [java]  1573: const       115 
     [java]      | 115 
     [java]  1578: putstatic   123 
     [java]      | 
     [java]  1581: const       116 
     [java]      | 116 
     [java]  1586: putstatic   124 
     [java]      | 
     [java]  1589: const       97 
     [java]      | 97 
     [java]  1594: putstatic   125 
     [java]      | 
     [java]  1597: const       118 
     [java]      | 118 
     [java]  1602: putstatic   126 
     [java]      | 
     [java]  1605: const       105 
     [java]      | 105 
     [java]  1610: putstatic   127 
     [java]      | 
     [java]  1613: const       80 
     [java]      | 80 
     [java]  1618: putstatic   128 
     [java]      | 
     [java]  1621: const       111 
     [java]      | 111 
     [java]  1626: putstatic   129 
     [java]      | 
     [java]  1629: const       108 
     [java]      | 108 
     [java]  1634: putstatic   130 
     [java]      | 
     [java]  1637: const       117 
     [java]      | 117 
     [java]  1642: putstatic   131 
     [java]      | 
     [java]  1645: const       112 
     [java]      | 112 
     [java]  1650: putstatic   132 
     [java]      | 
     [java]  1653: const       114 
     [java]      | 114 
     [java]  1658: putstatic   133 
     [java]      | 
     [java]  1661: const       101 
     [java]      | 101 
     [java]  1666: putstatic   134 
     [java]      | 
     [java]  1669: const       99 
     [java]      | 99 
     [java]  1674: putstatic   135 
     [java]      | 
     [java]  1677: const       110 
     [java]      | 110 
     [java]  1682: putstatic   136 
     [java]      | 
     [java]  1685: const       105 
     [java]      | 105 
     [java]  1690: putstatic   137 
     [java]      | 
     [java]  1693: const       107 
     [java]      | 107 
     [java]  1698: putstatic   138 
     [java]      | 
     [java]  1701: const_m1    
     [java]      | -1 
     [java]  1702: putstatic   139 
     [java]      | 
     [java]  1705: const       248 
     [java]      | 248 
     [java]  1710: putstatic   140 
     [java]      | 
     [java]  1713: const       122 
     [java]      | 122 
     [java]  1718: putstatic   141 
     [java]      | 
     [java]  1721: const       97 
     [java]      | 97 
     [java]  1726: putstatic   142 
     [java]      | 
     [java]  1729: const       112 
     [java]      | 112 
     [java]  1734: putstatic   143 
     [java]      | 
     [java]  1737: const       114 
     [java]      | 114 
     [java]  1742: putstatic   144 
     [java]      | 
     [java]  1745: const       101 
     [java]      | 101 
     [java]  1750: putstatic   145 
     [java]      | 
     [java]  1753: const       109 
     [java]      | 109 
     [java]  1758: putstatic   146 
     [java]      | 
     [java]  1761: const       105 
     [java]      | 105 
     [java]  1766: putstatic   147 
     [java]      | 
     [java]  1769: const       110 
     [java]      | 110 
     [java]  1774: putstatic   148 
     [java]      | 
     [java]  1777: const       97 
     [java]      | 97 
     [java]  1782: putstatic   149 
     [java]      | 
     [java]  1785: const_m1    
     [java]      | -1 
     [java]  1786: putstatic   150 
     [java]      | 
     [java]  1789: const       321 
     [java]      | 321 
     [java]  1794: putstatic   151 
     [java]      | 
     [java]  1797: const       104 
     [java]      | 104 
     [java]  1802: putstatic   152 
     [java]      | 
     [java]  1805: const       105 
     [java]      | 105 
     [java]  1810: putstatic   153 
     [java]      | 
     [java]  1813: const       84 
     [java]      | 84 
     [java]  1818: putstatic   154 
     [java]      | 
     [java]  1821: const       104 
     [java]      | 104 
     [java]  1826: putstatic   155 
     [java]      | 
     [java]  1829: const       105 
     [java]      | 105 
     [java]  1834: putstatic   156 
     [java]      | 
     [java]  1837: const       115 
     [java]      | 115 
     [java]  1842: putstatic   157 
     [java]      | 
     [java]  1845: const_m1    
     [java]      | -1 
     [java]  1846: putstatic   158 
     [java]      | 
     [java]  1849: const       51 
     [java]      | 51 
     [java]  1854: putstatic   159 
     [java]      | 
     [java]  1857: const       117 
     [java]      | 117 
     [java]  1862: putstatic   160 
     [java]      | 
     [java]  1865: const       99 
     [java]      | 99 
     [java]  1870: putstatic   161 
     [java]      | 
     [java]  1873: const       105 
     [java]      | 105 
     [java]  1878: putstatic   162 
     [java]      | 
     [java]  1881: const       116 
     [java]      | 116 
     [java]  1886: putstatic   163 
     [java]      | 
     [java]  1889: const       97 
     [java]      | 97 
     [java]  1894: putstatic   164 
     [java]      | 
     [java]  1897: const       106 
     [java]      | 106 
     [java]  1902: putstatic   165 
     [java]      | 
     [java]  1905: const       84 
     [java]      | 84 
     [java]  1910: putstatic   166 
     [java]      | 
     [java]  1913: const       101 
     [java]      | 101 
     [java]  1918: putstatic   167 
     [java]      | 
     [java]  1921: const       122 
     [java]      | 122 
     [java]  1926: putstatic   168 
     [java]      | 
     [java]  1929: const       105 
     [java]      | 105 
     [java]  1934: putstatic   169 
     [java]      | 
     [java]  1937: const       110 
     [java]      | 110 
     [java]  1942: putstatic   170 
     [java]      | 
     [java]  1945: const       117 
     [java]      | 117 
     [java]  1950: putstatic   171 
     [java]      | 
     [java]  1953: const_m1    
     [java]      | -1 
     [java]  1954: putstatic   172 
     [java]      | 
     [java]  1957: const       84 
     [java]      | 84 
     [java]  1962: putstatic   173 
     [java]      | 
     [java]  1965: const       81 
     [java]      | 81 
     [java]  1970: putstatic   174 
     [java]      | 
     [java]  1973: const_m1    
     [java]      | -1 
     [java]  1974: putstatic   175 
     [java]      | 
     [java]  1977: const       102 
     [java]      | 102 
     [java]  1982: putstatic   176 
     [java]      | 
     [java]  1985: const       112 
     [java]      | 112 
     [java]  1990: putstatic   177 
     [java]      | 
     [java]  1993: const       111 
     [java]      | 111 
     [java]  1998: putstatic   178 
     [java]      | 
     [java]  2001: const       115 
     [java]      | 115 
     [java]  2006: putstatic   179 
     [java]      | 
     [java]  2009: const       116 
     [java]      | 116 
     [java]  2014: putstatic   180 
     [java]      | 
     [java]  2017: const       97 
     [java]      | 97 
     [java]  2022: putstatic   181 
     [java]      | 
     [java]  2025: const       118 
     [java]      | 118 
     [java]  2030: putstatic   182 
     [java]      | 
     [java]  2033: const       105 
     [java]      | 105 
     [java]  2038: putstatic   183 
     [java]      | 
     [java]  2041: const       86 
     [java]      | 86 
     [java]  2046: putstatic   184 
     [java]      | 
     [java]  2049: const       114 
     [java]      | 114 
     [java]  2054: putstatic   185 
     [java]      | 
     [java]  2057: const       115 
     [java]      | 115 
     [java]  2062: putstatic   186 
     [java]      | 
     [java]  2065: const       116 
     [java]      | 116 
     [java]  2070: putstatic   187 
     [java]      | 
     [java]  2073: const       117 
     [java]      | 117 
     [java]  2078: putstatic   188 
     [java]      | 
     [java]  2081: const_m1    
     [java]      | -1 
     [java]  2082: putstatic   189 
     [java]      | 
     [java]  2085: const       160 
     [java]      | 160 
     [java]  2090: putstatic   190 
     [java]      | 
     [java]  2093: const       100 
     [java]      | 100 
     [java]  2098: putstatic   191 
     [java]      | 
     [java]  2101: const       111 
     [java]      | 111 
     [java]  2106: putstatic   192 
     [java]      | 
     [java]  2109: const       104 
     [java]      | 104 
     [java]  2114: putstatic   193 
     [java]      | 
     [java]  2117: const       118 
     [java]      | 118 
     [java]  2122: putstatic   194 
     [java]      | 
     [java]  2125: const       86 
     [java]      | 86 
     [java]  2130: putstatic   195 
     [java]      | 
     [java]  2133: const       114 
     [java]      | 114 
     [java]  2138: putstatic   196 
     [java]      | 
     [java]  2141: const       115 
     [java]      | 115 
     [java]  2146: putstatic   197 
     [java]      | 
     [java]  2149: const       116 
     [java]      | 116 
     [java]  2154: putstatic   198 
     [java]      | 
     [java]  2157: const       117 
     [java]      | 117 
     [java]  2162: putstatic   199 
     [java]      | 
     [java]  2165: const_m1    
     [java]      | -1 
     [java]  2166: putstatic   200 
     [java]      | 
     [java]  2169: const       170 
     [java]      | 170 
     [java]  2174: putstatic   201 
     [java]      | 
     [java]  2177: const       100 
     [java]      | 100 
     [java]  2182: putstatic   202 
     [java]      | 
     [java]  2185: const       111 
     [java]      | 111 
     [java]  2190: putstatic   203 
     [java]      | 
     [java]  2193: const       104 
     [java]      | 104 
     [java]  2198: putstatic   204 
     [java]      | 
     [java]  2201: const       118 
     [java]      | 118 
     [java]  2206: putstatic   205 
     [java]      | 
     [java]  2209: const       84 
     [java]      | 84 
     [java]  2214: putstatic   206 
     [java]      | 
     [java]  2217: const       101 
     [java]      | 101 
     [java]  2222: putstatic   207 
     [java]      | 
     [java]  2225: const       122 
     [java]      | 122 
     [java]  2230: putstatic   208 
     [java]      | 
     [java]  2233: const       105 
     [java]      | 105 
     [java]  2238: putstatic   209 
     [java]      | 
     [java]  2241: const       110 
     [java]      | 110 
     [java]  2246: putstatic   210 
     [java]      | 
     [java]  2249: const       117 
     [java]      | 117 
     [java]  2254: putstatic   211 
     [java]      | 
     [java]  2257: const_m1    
     [java]      | -1 
     [java]  2258: putstatic   212 
     [java]      | 
     [java]  2261: const       181 
     [java]      | 181 
     [java]  2266: putstatic   213 
     [java]      | 
     [java]  2269: const       104 
     [java]      | 104 
     [java]  2274: putstatic   214 
     [java]      | 
     [java]  2277: const       105 
     [java]      | 105 
     [java]  2282: putstatic   215 
     [java]      | 
     [java]  2285: const       114 
     [java]      | 114 
     [java]  2290: putstatic   216 
     [java]      | 
     [java]  2293: const_m1    
     [java]      | -1 
     [java]  2294: putstatic   217 
     [java]      | 
     [java]  2297: const       192 
     [java]      | 192 
     [java]  2302: putstatic   218 
     [java]      | 
     [java]  2305: const       -2 
     [java]      | -2 
     [java]  2310: putstatic   219 
     [java]      | 
     [java]  2313: const       104 
     [java]      | 104 
     [java]  2318: putstatic   220 
     [java]      | 
     [java]  2321: const       105 
     [java]      | 105 
     [java]  2326: putstatic   221 
     [java]      | 
     [java]  2329: const_m1    
     [java]      | -1 
     [java]  2330: putstatic   222 
     [java]      | 
     [java]  2333: const       338 
     [java]      | 338 
     [java]  2338: putstatic   223 
     [java]      | 
     [java]  2341: const       112 
     [java]      | 112 
     [java]  2346: putstatic   224 
     [java]      | 
     [java]  2349: const       111 
     [java]      | 111 
     [java]  2354: putstatic   225 
     [java]      | 
     [java]  2357: const       115 
     [java]      | 115 
     [java]  2362: putstatic   226 
     [java]      | 
     [java]  2365: const       116 
     [java]      | 116 
     [java]  2370: putstatic   227 
     [java]      | 
     [java]  2373: const       97 
     [java]      | 97 
     [java]  2378: putstatic   228 
     [java]      | 
     [java]  2381: const       118 
     [java]      | 118 
     [java]  2386: putstatic   229 
     [java]      | 
     [java]  2389: const       105 
     [java]      | 105 
     [java]  2394: putstatic   230 
     [java]      | 
     [java]  2397: const       84 
     [java]      | 84 
     [java]  2402: putstatic   231 
     [java]      | 
     [java]  2405: const       101 
     [java]      | 101 
     [java]  2410: putstatic   232 
     [java]      | 
     [java]  2413: const       122 
     [java]      | 122 
     [java]  2418: putstatic   233 
     [java]      | 
     [java]  2421: const       105 
     [java]      | 105 
     [java]  2426: putstatic   234 
     [java]      | 
     [java]  2429: const       110 
     [java]      | 110 
     [java]  2434: putstatic   235 
     [java]      | 
     [java]  2437: const       117 
     [java]      | 117 
     [java]  2442: putstatic   236 
     [java]      | 
     [java]  2445: const_m1    
     [java]      | -1 
     [java]  2446: putstatic   237 
     [java]      | 
     [java]  2449: const       364 
     [java]      | 364 
     [java]  2454: putstatic   238 
     [java]      | 
     [java]  2457: const       112 
     [java]      | 112 
     [java]  2462: putstatic   239 
     [java]      | 
     [java]  2465: const       111 
     [java]      | 111 
     [java]  2470: putstatic   240 
     [java]      | 
     [java]  2473: const       115 
     [java]      | 115 
     [java]  2478: putstatic   241 
     [java]      | 
     [java]  2481: const       116 
     [java]      | 116 
     [java]  2486: putstatic   242 
     [java]      | 
     [java]  2489: const       97 
     [java]      | 97 
     [java]  2494: putstatic   243 
     [java]      | 
     [java]  2497: const       118 
     [java]      | 118 
     [java]  2502: putstatic   244 
     [java]      | 
     [java]  2505: const       105 
     [java]      | 105 
     [java]  2510: putstatic   245 
     [java]      | 
     [java]  2513: const       83 
     [java]      | 83 
     [java]  2518: putstatic   246 
     [java]      | 
     [java]  2521: const       116 
     [java]      | 116 
     [java]  2526: putstatic   247 
     [java]      | 
     [java]  2529: const       114 
     [java]      | 114 
     [java]  2534: putstatic   248 
     [java]      | 
     [java]  2537: const       97 
     [java]      | 97 
     [java]  2542: putstatic   249 
     [java]      | 
     [java]  2545: const       110 
     [java]      | 110 
     [java]  2550: putstatic   250 
     [java]      | 
     [java]  2553: const       105 
     [java]      | 105 
     [java]  2558: putstatic   251 
     [java]      | 
     [java]  2561: const       99 
     [java]      | 99 
     [java]  2566: putstatic   252 
     [java]      | 
     [java]  2569: const       101 
     [java]      | 101 
     [java]  2574: putstatic   253 
     [java]      | 
     [java]  2577: const_m1    
     [java]      | -1 
     [java]  2578: putstatic   254 
     [java]      | 
     [java]  2581: const       374 
     [java]      | 374 
     [java]  2586: putstatic   255 
     [java]      | 
     [java]  2589: const       122 
     [java]      | 122 
     [java]  2594: putstatic   256 
     [java]      | 
     [java]  2597: const       97 
     [java]      | 97 
     [java]  2602: putstatic   257 
     [java]      | 
     [java]  2605: const       112 
     [java]      | 112 
     [java]  2610: putstatic   258 
     [java]      | 
     [java]  2613: const       114 
     [java]      | 114 
     [java]  2618: putstatic   259 
     [java]      | 
     [java]  2621: const       101 
     [java]      | 101 
     [java]  2626: putstatic   260 
     [java]      | 
     [java]  2629: const       109 
     [java]      | 109 
     [java]  2634: putstatic   261 
     [java]      | 
     [java]  2637: const       105 
     [java]      | 105 
     [java]  2642: putstatic   262 
     [java]      | 
     [java]  2645: const       110 
     [java]      | 110 
     [java]  2650: putstatic   263 
     [java]      | 
     [java]  2653: const       97 
     [java]      | 97 
     [java]  2658: putstatic   264 
     [java]      | 
     [java]  2661: const_m1    
     [java]      | -1 
     [java]  2662: putstatic   265 
     [java]      | 
     [java]  2665: const       403 
     [java]      | 403 
     [java]  2670: putstatic   266 
     [java]      | 
     [java]  2673: const       104 
     [java]      | 104 
     [java]  2678: putstatic   267 
     [java]      | 
     [java]  2681: const       105 
     [java]      | 105 
     [java]  2686: putstatic   268 
     [java]      | 
     [java]  2689: const       114 
     [java]      | 114 
     [java]  2694: putstatic   269 
     [java]      | 
     [java]  2697: const_m1    
     [java]      | -1 
     [java]  2698: putstatic   270 
     [java]      | 
     [java]  2701: const       426 
     [java]      | 426 
     [java]  2706: putstatic   271 
     [java]      | 
     [java]  2709: const       104 
     [java]      | 104 
     [java]  2714: putstatic   272 
     [java]      | 
     [java]  2717: const       105 
     [java]      | 105 
     [java]  2722: putstatic   273 
     [java]      | 
     [java]  2725: const       84 
     [java]      | 84 
     [java]  2730: putstatic   274 
     [java]      | 
     [java]  2733: const       104 
     [java]      | 104 
     [java]  2738: putstatic   275 
     [java]      | 
     [java]  2741: const       105 
     [java]      | 105 
     [java]  2746: putstatic   276 
     [java]      | 
     [java]  2749: const       115 
     [java]      | 115 
     [java]  2754: putstatic   277 
     [java]      | 
     [java]  2757: const_m1    
     [java]      | -1 
     [java]  2758: putstatic   278 
     [java]      | 
     [java]  2761: const       51 
     [java]      | 51 
     [java]  2766: putstatic   279 
     [java]      | 
     [java]  2769: const       117 
     [java]      | 117 
     [java]  2774: putstatic   280 
     [java]      | 
     [java]  2777: const       99 
     [java]      | 99 
     [java]  2782: putstatic   281 
     [java]      | 
     [java]  2785: const       105 
     [java]      | 105 
     [java]  2790: putstatic   282 
     [java]      | 
     [java]  2793: const       116 
     [java]      | 116 
     [java]  2798: putstatic   283 
     [java]      | 
     [java]  2801: const       97 
     [java]      | 97 
     [java]  2806: putstatic   284 
     [java]      | 
     [java]  2809: const       106 
     [java]      | 106 
     [java]  2814: putstatic   285 
     [java]      | 
     [java]  2817: const       84 
     [java]      | 84 
     [java]  2822: putstatic   286 
     [java]      | 
     [java]  2825: const       101 
     [java]      | 101 
     [java]  2830: putstatic   287 
     [java]      | 
     [java]  2833: const       122 
     [java]      | 122 
     [java]  2838: putstatic   288 
     [java]      | 
     [java]  2841: const       105 
     [java]      | 105 
     [java]  2846: putstatic   289 
     [java]      | 
     [java]  2849: const       110 
     [java]      | 110 
     [java]  2854: putstatic   290 
     [java]      | 
     [java]  2857: const       117 
     [java]      | 117 
     [java]  2862: putstatic   291 
     [java]      | 
     [java]  2865: const_m1    
     [java]      | -1 
     [java]  2866: putstatic   292 
     [java]      | 
     [java]  2869: const       84 
     [java]      | 84 
     [java]  2874: putstatic   293 
     [java]      | 
     [java]  2877: const       81 
     [java]      | 81 
     [java]  2882: putstatic   294 
     [java]      | 
     [java]  2885: const_m1    
     [java]      | -1 
     [java]  2886: putstatic   295 
     [java]      | 
     [java]  2889: const       102 
     [java]      | 102 
     [java]  2894: putstatic   296 
     [java]      | 
     [java]  2897: const       112 
     [java]      | 112 
     [java]  2902: putstatic   297 
     [java]      | 
     [java]  2905: const       111 
     [java]      | 111 
     [java]  2910: putstatic   298 
     [java]      | 
     [java]  2913: const       115 
     [java]      | 115 
     [java]  2918: putstatic   299 
     [java]      | 
     [java]  2921: const       116 
     [java]      | 116 
     [java]  2926: putstatic   300 
     [java]      | 
     [java]  2929: const       97 
     [java]      | 97 
     [java]  2934: putstatic   301 
     [java]      | 
     [java]  2937: const       118 
     [java]      | 118 
     [java]  2942: putstatic   302 
     [java]      | 
     [java]  2945: const       105 
     [java]      | 105 
     [java]  2950: putstatic   303 
     [java]      | 
     [java]  2953: const       86 
     [java]      | 86 
     [java]  2958: putstatic   304 
     [java]      | 
     [java]  2961: const       114 
     [java]      | 114 
     [java]  2966: putstatic   305 
     [java]      | 
     [java]  2969: const       115 
     [java]      | 115 
     [java]  2974: putstatic   306 
     [java]      | 
     [java]  2977: const       116 
     [java]      | 116 
     [java]  2982: putstatic   307 
     [java]      | 
     [java]  2985: const       117 
     [java]      | 117 
     [java]  2990: putstatic   308 
     [java]      | 
     [java]  2993: const_m1    
     [java]      | -1 
     [java]  2994: putstatic   309 
     [java]      | 
     [java]  2997: const       160 
     [java]      | 160 
     [java]  3002: putstatic   310 
     [java]      | 
     [java]  3005: const       100 
     [java]      | 100 
     [java]  3010: putstatic   311 
     [java]      | 
     [java]  3013: const       111 
     [java]      | 111 
     [java]  3018: putstatic   312 
     [java]      | 
     [java]  3021: const       104 
     [java]      | 104 
     [java]  3026: putstatic   313 
     [java]      | 
     [java]  3029: const       118 
     [java]      | 118 
     [java]  3034: putstatic   314 
     [java]      | 
     [java]  3037: const       86 
     [java]      | 86 
     [java]  3042: putstatic   315 
     [java]      | 
     [java]  3045: const       114 
     [java]      | 114 
     [java]  3050: putstatic   316 
     [java]      | 
     [java]  3053: const       115 
     [java]      | 115 
     [java]  3058: putstatic   317 
     [java]      | 
     [java]  3061: const       116 
     [java]      | 116 
     [java]  3066: putstatic   318 
     [java]      | 
     [java]  3069: const       117 
     [java]      | 117 
     [java]  3074: putstatic   319 
     [java]      | 
     [java]  3077: const_m1    
     [java]      | -1 
     [java]  3078: putstatic   320 
     [java]      | 
     [java]  3081: const       170 
     [java]      | 170 
     [java]  3086: putstatic   321 
     [java]      | 
     [java]  3089: const       100 
     [java]      | 100 
     [java]  3094: putstatic   322 
     [java]      | 
     [java]  3097: const       111 
     [java]      | 111 
     [java]  3102: putstatic   323 
     [java]      | 
     [java]  3105: const       104 
     [java]      | 104 
     [java]  3110: putstatic   324 
     [java]      | 
     [java]  3113: const       118 
     [java]      | 118 
     [java]  3118: putstatic   325 
     [java]      | 
     [java]  3121: const       84 
     [java]      | 84 
     [java]  3126: putstatic   326 
     [java]      | 
     [java]  3129: const       101 
     [java]      | 101 
     [java]  3134: putstatic   327 
     [java]      | 
     [java]  3137: const       122 
     [java]      | 122 
     [java]  3142: putstatic   328 
     [java]      | 
     [java]  3145: const       105 
     [java]      | 105 
     [java]  3150: putstatic   329 
     [java]      | 
     [java]  3153: const       110 
     [java]      | 110 
     [java]  3158: putstatic   330 
     [java]      | 
     [java]  3161: const       117 
     [java]      | 117 
     [java]  3166: putstatic   331 
     [java]      | 
     [java]  3169: const_m1    
     [java]      | -1 
     [java]  3170: putstatic   332 
     [java]      | 
     [java]  3173: const       181 
     [java]      | 181 
     [java]  3178: putstatic   333 
     [java]      | 
     [java]  3181: const       -2 
     [java]      | -2 
     [java]  3186: putstatic   334 
     [java]      | 
     [java]  3189: enter       0 9 
     [java]      | 
     [java]  3192: const       6 
     [java]      | 6 
     [java]  3197: newarray    1 
     [java]      | 2 
     [java]  3199: store_0     
     [java]      | 
     [java]  3200: new         24 
     [java]      | 8 
     [java]  3203: dup         
     [java]      | 8 8 
     [java]  3204: const       102 
     [java]      | 8 8 102 
     [java]  3209: putfield    0 
     [java]      | 8 
     [java]  3212: store_2     
     [java]      | 
     [java]  3213: new         24 
     [java]      | 14 
     [java]  3216: dup         
     [java]      | 14 14 
     [java]  3217: const       102 
     [java]      | 14 14 102 
     [java]  3222: putfield    0 
     [java]      | 14 
     [java]  3225: store_3     
     [java]      | 
     [java]  3226: new         24 
     [java]      | 20 
     [java]  3229: dup         
     [java]      | 20 20 
     [java]  3230: const       102 
     [java]      | 20 20 102 
     [java]  3235: putfield    0 
     [java]      | 20 
     [java]  3238: store       4 
     [java]      | 
     [java]  3240: new         32 
     [java]      | 26 
     [java]  3243: dup         
     [java]      | 26 26 
     [java]  3244: const       220 
     [java]      | 26 26 220 
     [java]  3249: putfield    0 
     [java]      | 26 
     [java]  3252: store       5 
     [java]      | 
     [java]  3254: new         32 
     [java]      | 34 
     [java]  3257: dup         
     [java]      | 34 34 
     [java]  3258: const       220 
     [java]      | 34 34 220 
     [java]  3263: putfield    0 
     [java]      | 34 
     [java]  3266: store       6 
     [java]      | 
     [java]  3268: new         32 
     [java]      | 42 
     [java]  3271: dup         
     [java]      | 42 42 
     [java]  3272: const       220 
     [java]      | 42 42 220 
     [java]  3277: putfield    0 
     [java]      | 42 
     [java]  3280: store       7 
     [java]      | 
     [java]  3282: load_2      
     [java]      | 8 
     [java]  3283: const_1     
     [java]      | 8 1 
     [java]  3284: load_2      
     [java]      | 8 1 8 
     [java]  3285: getfield    0 
     [java]      | 8 1 102 
     [java]  3288: invokevirtual 112 112 111 115 116 97 118 105 80 112 111 115 116 97 118 105 80 111 108 117 112 114 101 99 110 105 107 -1 
     [java]      | 8 1 
     [java]   248: enter       2 2 
     [java]      | 
     [java]   251: load_0      
     [java]      | 8 
     [java]   252: load_1      
     [java]      | 8 1 
     [java]   253: putfield    5 
     [java]      | 
     [java]   256: load_0      
     [java]      | 8 
     [java]   257: const       115 
     [java]      | 8 115 
     [java]   262: load_0      
     [java]      | 8 115 8 
     [java]   263: getfield    0 
     [java]      | 8 115 102 
     [java]   266: invokevirtual 112 112 111 115 116 97 118 105 86 112 111 115 116 97 118 105 86 112 112 112 112 112 111 115 116 97 118 105 86 114 115 116 117 -1 
     [java]      | 8 115 
     [java]   160: enter       2 2 
     [java]      | 
     [java]   163: load_0      
     [java]      | 8 
     [java]   164: load_1      
     [java]      | 8 115 
     [java]   165: putfield    4 
     [java]      | 
     [java]   168: exit        
     [java]      | 
     [java]   169: return      
     [java]      | 
     [java]   319: exit        
     [java]      | 
     [java]   320: return      
     [java]      | 
     [java]  3365: load_3      
     [java]      | 14 
     [java]  3366: const_2     
     [java]      | 14 2 
     [java]  3367: load_3      
     [java]      | 14 2 14 
     [java]  3368: getfield    0 
     [java]      | 14 2 102 
     [java]  3371: invokevirtual 112 112 111 115 116 97 118 105 80 112 111 115 116 97 118 105 80 111 108 117 112 114 101 99 110 105 107 -1 
     [java]      | 14 2 
     [java]   248: enter       2 2 
     [java]      | 
     [java]   251: load_0      
     [java]      | 14 
     [java]   252: load_1      
     [java]      | 14 2 
     [java]   253: putfield    5 
     [java]      | 
     [java]   256: load_0      
     [java]      | 14 
     [java]   257: const       115 
     [java]      | 14 115 
     [java]   262: load_0      
     [java]      | 14 115 14 
     [java]   263: getfield    0 
     [java]      | 14 115 102 
     [java]   266: invokevirtual 112 112 111 115 116 97 118 105 86 112 111 115 116 97 118 105 86 112 112 112 112 112 111 115 116 97 118 105 86 114 115 116 117 -1 
     [java]      | 14 115 
     [java]   160: enter       2 2 
     [java]      | 
     [java]   163: load_0      
     [java]      | 14 
     [java]   164: load_1      
     [java]      | 14 115 
     [java]   165: putfield    4 
     [java]      | 
     [java]   168: exit        
     [java]      | 
     [java]   169: return      
     [java]      | 
     [java]   319: exit        
     [java]      | 
     [java]   320: return      
     [java]      | 
     [java]  3448: load        4 
     [java]      | 20 
     [java]  3450: const_3     
     [java]      | 20 3 
     [java]  3451: load        4 
     [java]      | 20 3 20 
     [java]  3453: getfield    0 
     [java]      | 20 3 102 
     [java]  3456: invokevirtual 112 112 111 115 116 97 118 105 80 112 111 115 116 97 118 105 80 111 108 117 112 114 101 99 110 105 107 -1 
     [java]      | 20 3 
     [java]   248: enter       2 2 
     [java]      | 
     [java]   251: load_0      
     [java]      | 20 
     [java]   252: load_1      
     [java]      | 20 3 
     [java]   253: putfield    5 
     [java]      | 
     [java]   256: load_0      
     [java]      | 20 
     [java]   257: const       115 
     [java]      | 20 115 
     [java]   262: load_0      
     [java]      | 20 115 20 
     [java]   263: getfield    0 
     [java]      | 20 115 102 
     [java]   266: invokevirtual 112 112 111 115 116 97 118 105 86 112 111 115 116 97 118 105 86 112 112 112 112 112 111 115 116 97 118 105 86 114 115 116 117 -1 
     [java]      | 20 115 
     [java]   160: enter       2 2 
     [java]      | 
     [java]   163: load_0      
     [java]      | 20 
     [java]   164: load_1      
     [java]      | 20 115 
     [java]   165: putfield    4 
     [java]      | 
     [java]   168: exit        
     [java]      | 
     [java]   169: return      
     [java]      | 
     [java]   319: exit        
     [java]      | 
     [java]   320: return      
     [java]      | 
     [java]  3533: load        5 
     [java]      | 26 
     [java]  3535: const_1     
     [java]      | 26 1 
     [java]  3536: const_2     
     [java]      | 26 1 2 
     [java]  3537: const_3     
     [java]      | 26 1 2 3 
     [java]  3538: load        5 
     [java]      | 26 1 2 3 26 
     [java]  3540: getfield    0 
     [java]      | 26 1 2 3 220 
     [java]  3543: invokevirtual 112 112 111 115 116 97 118 105 83 112 111 115 116 97 118 105 83 116 114 97 110 105 99 101 -1 
     [java]      | 26 1 2 3 
     [java]   374: enter       4 4 
     [java]      | 
     [java]   377: load_0      
     [java]      | 26 
     [java]   378: load_1      
     [java]      | 26 1 
     [java]   379: putfield    5 
     [java]      | 
     [java]   382: load_0      
     [java]      | 26 
     [java]   383: load_2      
     [java]      | 26 2 
     [java]   384: putfield    6 
     [java]      | 
     [java]   387: load_0      
     [java]      | 26 
     [java]   388: load_3      
     [java]      | 26 3 
     [java]   389: putfield    7 
     [java]      | 
     [java]   392: load_0      
     [java]      | 26 
     [java]   393: const       107 
     [java]      | 26 107 
     [java]   398: putfield    4 
     [java]      | 
     [java]   401: exit        
     [java]      | 
     [java]   402: return      
     [java]      | 
     [java]  3608: load        6 
     [java]      | 34 
     [java]  3610: const_2     
     [java]      | 34 2 
     [java]  3611: const_3     
     [java]      | 34 2 3 
     [java]  3612: const_4     
     [java]      | 34 2 3 4 
     [java]  3613: load        6 
     [java]      | 34 2 3 4 34 
     [java]  3615: getfield    0 
     [java]      | 34 2 3 4 220 
     [java]  3618: invokevirtual 112 112 111 115 116 97 118 105 83 112 111 115 116 97 118 105 83 116 114 97 110 105 99 101 -1 
     [java]      | 34 2 3 4 
     [java]   374: enter       4 4 
     [java]      | 
     [java]   377: load_0      
     [java]      | 34 
     [java]   378: load_1      
     [java]      | 34 2 
     [java]   379: putfield    5 
     [java]      | 
     [java]   382: load_0      
     [java]      | 34 
     [java]   383: load_2      
     [java]      | 34 3 
     [java]   384: putfield    6 
     [java]      | 
     [java]   387: load_0      
     [java]      | 34 
     [java]   388: load_3      
     [java]      | 34 4 
     [java]   389: putfield    7 
     [java]      | 
     [java]   392: load_0      
     [java]      | 34 
     [java]   393: const       107 
     [java]      | 34 107 
     [java]   398: putfield    4 
     [java]      | 
     [java]   401: exit        
     [java]      | 
     [java]   402: return      
     [java]      | 
     [java]  3683: load        7 
     [java]      | 42 
     [java]  3685: const_3     
     [java]      | 42 3 
     [java]  3686: const_4     
     [java]      | 42 3 4 
     [java]  3687: const_5     
     [java]      | 42 3 4 5 
     [java]  3688: load        7 
     [java]      | 42 3 4 5 42 
     [java]  3690: getfield    0 
     [java]      | 42 3 4 5 220 
     [java]  3693: invokevirtual 112 112 111 115 116 97 118 105 83 112 111 115 116 97 118 105 83 116 114 97 110 105 99 101 -1 
     [java]      | 42 3 4 5 
     [java]   374: enter       4 4 
     [java]      | 
     [java]   377: load_0      
     [java]      | 42 
     [java]   378: load_1      
     [java]      | 42 3 
     [java]   379: putfield    5 
     [java]      | 
     [java]   382: load_0      
     [java]      | 42 
     [java]   383: load_2      
     [java]      | 42 4 
     [java]   384: putfield    6 
     [java]      | 
     [java]   387: load_0      
     [java]      | 42 
     [java]   388: load_3      
     [java]      | 42 5 
     [java]   389: putfield    7 
     [java]      | 
     [java]   392: load_0      
     [java]      | 42 
     [java]   393: const       107 
     [java]      | 42 107 
     [java]   398: putfield    4 
     [java]      | 
     [java]   401: exit        
     [java]      | 
     [java]   402: return      
     [java]      | 
     [java]  3758: load_0      
     [java]      | 2 
     [java]  3759: const_0     
     [java]      | 2 0 
     [java]  3760: load_2      
     [java]      | 2 0 8 
     [java]  3761: astore      
     [java] Arraylength = 6
     [java] Address = 2
     [java] Index = 0
     [java] Value = 8
     [java] 
     [java]      | 
     [java]  3762: load_0      
     [java]      | 2 
     [java]  3763: const_2     
     [java]      | 2 2 
     [java]  3764: load_3      
     [java]      | 2 2 14 
     [java]  3765: astore      
     [java] Arraylength = 6
     [java] Address = 2
     [java] Index = 2
     [java] Value = 14
     [java] 
     [java]      | 
     [java]  3766: load_0      
     [java]      | 2 
     [java]  3767: const_4     
     [java]      | 2 4 
     [java]  3768: load        4 
     [java]      | 2 4 20 
     [java]  3770: astore      
     [java] Arraylength = 6
     [java] Address = 2
     [java] Index = 4
     [java] Value = 20
     [java] 
     [java]      | 
     [java]  3771: load_0      
     [java]      | 2 
     [java]  3772: const_1     
     [java]      | 2 1 
     [java]  3773: load        5 
     [java]      | 2 1 26 
     [java]  3775: astore      
     [java] Arraylength = 6
     [java] Address = 2
     [java] Index = 1
     [java] Value = 26
     [java] 
     [java]      | 
     [java]  3776: load_0      
     [java]      | 2 
     [java]  3777: const_3     
     [java]      | 2 3 
     [java]  3778: load        6 
     [java]      | 2 3 34 
     [java]  3780: astore      
     [java] Arraylength = 6
     [java] Address = 2
     [java] Index = 3
     [java] Value = 34
     [java] 
     [java]      | 
     [java]  3781: load_0      
     [java]      | 2 
     [java]  3782: const_5     
     [java]      | 2 5 
     [java]  3783: load        7 
     [java]      | 2 5 42 
     [java]  3785: astore      
     [java] Arraylength = 6
     [java] Address = 2
     [java] Index = 5
     [java] Value = 42
     [java] 
     [java]      | 
     [java]  3786: load        5 
     [java]      | 26 
     [java]  3788: new         20 
     [java]      | 26 50 
     [java]  3791: dup         
     [java]      | 26 50 50 
     [java]  3792: const_4     
     [java]      | 26 50 50 4 
     [java]  3793: putfield    0 
     [java]      | 26 50 
     [java]  3796: load        5 
     [java]      | 26 50 26 
     [java]  3798: getfield    0 
     [java]      | 26 50 220 
     [java]  3801: invokevirtual 104 105 114 104 104 104 104 105 114 -1 
     [java]      | 26 50 
     [java]   426: enter       2 2 
     [java]      | 
     [java]   429: load_1      
     [java]      | 50 
     [java]   430: const       4444 
     [java]      | 50 4444 
     [java]   435: putfield    3 
     [java]      | 
     [java]   438: load_1      
     [java]      | 50 
     [java]   439: getfield    3 
     [java]      | 4444 
     [java]   442: const_5     
     [java]      | 4444 5 
     [java]   443: print        4444
     [java]      | 
     [java]   444: load_1      
     [java]      | 50 
     [java]   445: load_1      
     [java]      | 50 50 
     [java]   446: getfield    0 
     [java]      | 50 4 
     [java]   449: invokevirtual 104 105 84 104 105 84 104 105 115 -1 
     [java]      | 50 
     [java]    51: enter       1 1 
     [java]      | 
     [java]    54: load_0      
     [java]      | 50 
     [java]    55: load_0      
     [java]      | 50 50 
     [java]    56: getfield    0 
     [java]      | 50 4 
     [java]    59: invokevirtual 104 105 -1 
     [java]      | 50 
     [java]    25: enter       1 1 
     [java]      | 
     [java]    28: const       112 
     [java]      | 112 
     [java]    33: const_1     
     [java]      | 112 1 
     [java]    34: bprint      p
     [java]      | 
     [java]    35: const       105 
     [java]      | 105 
     [java]    40: const_1     
     [java]      | 105 1 
     [java]    41: bprint      i
     [java]      | 
     [java]    42: const       10 
     [java]      | 10 
     [java]    47: const_1     
     [java]      | 10 1 
     [java]    48: bprint      
     [java] 
     [java]      | 
     [java]    49: exit        
     [java]      | 
     [java]    50: return      
     [java]      | 
     [java]    72: exit        
     [java]      | 
     [java]    73: return      
     [java]      | 
     [java]   478: exit        
     [java]      | 
     [java]   479: return      
     [java]      | 
     [java]  3818: load        5 
     [java]      | 26 
     [java]  3820: new         24 
     [java]      | 26 55 
     [java]  3823: dup         
     [java]      | 26 55 55 
     [java]  3824: const       102 
     [java]      | 26 55 55 102 
     [java]  3829: putfield    0 
     [java]      | 26 55 
     [java]  3832: load        5 
     [java]      | 26 55 26 
     [java]  3834: getfield    0 
     [java]      | 26 55 220 
     [java]  3837: invokevirtual 104 105 114 104 104 104 104 105 114 -1 
     [java]      | 26 55 
     [java]   426: enter       2 2 
     [java]      | 
     [java]   429: load_1      
     [java]      | 55 
     [java]   430: const       4444 
     [java]      | 55 4444 
     [java]   435: putfield    3 
     [java]      | 
     [java]   438: load_1      
     [java]      | 55 
     [java]   439: getfield    3 
     [java]      | 4444 
     [java]   442: const_5     
     [java]      | 4444 5 
     [java]   443: print        4444
     [java]      | 
     [java]   444: load_1      
     [java]      | 55 
     [java]   445: load_1      
     [java]      | 55 55 
     [java]   446: getfield    0 
     [java]      | 55 102 
     [java]   449: invokevirtual 104 105 84 104 104 104 104 105 84 104 105 115 -1 
     [java]      | 55 
     [java]    51: enter       1 1 
     [java]      | 
     [java]    54: load_0      
     [java]      | 55 
     [java]    55: load_0      
     [java]      | 55 55 
     [java]    56: getfield    0 
     [java]      | 55 102 
     [java]    59: invokevirtual 104 105 -1 
     [java]      | 55 
     [java]   212: enter       1 1 
     [java]      | 
     [java]   215: const       115 
     [java]      | 115 
     [java]   220: const_1     
     [java]      | 115 1 
     [java]   221: bprint      s
     [java]      | 
     [java]   222: const       105 
     [java]      | 105 
     [java]   227: const_1     
     [java]      | 105 1 
     [java]   228: bprint      i
     [java]      | 
     [java]   229: const       10 
     [java]      | 10 
     [java]   234: const_1     
     [java]      | 10 1 
     [java]   235: bprint      
     [java] 
     [java]      | 
     [java]   236: exit        
     [java]      | 
     [java]   237: return      
     [java]      | 
     [java]    72: exit        
     [java]      | 
     [java]    73: return      
     [java]      | 
     [java]   478: exit        
     [java]      | 
     [java]   479: return      
     [java]      | 
     [java]  3854: load        5 
     [java]      | 26 
     [java]  3856: new         32 
     [java]      | 26 61 
     [java]  3859: dup         
     [java]      | 26 61 61 
     [java]  3860: const       220 
     [java]      | 26 61 61 220 
     [java]  3865: putfield    0 
     [java]      | 26 61 
     [java]  3868: load        5 
     [java]      | 26 61 26 
     [java]  3870: getfield    0 
     [java]      | 26 61 220 
     [java]  3873: invokevirtual 104 105 114 104 104 104 104 105 114 -1 
     [java]      | 26 61 
     [java]   426: enter       2 2 
     [java]      | 
     [java]   429: load_1      
     [java]      | 61 
     [java]   430: const       4444 
     [java]      | 61 4444 
     [java]   435: putfield    3 
     [java]      | 
     [java]   438: load_1      
     [java]      | 61 
     [java]   439: getfield    3 
     [java]      | 4444 
     [java]   442: const_5     
     [java]      | 4444 5 
     [java]   443: print        4444
     [java]      | 
     [java]   444: load_1      
     [java]      | 61 
     [java]   445: load_1      
     [java]      | 61 61 
     [java]   446: getfield    0 
     [java]      | 61 220 
     [java]   449: invokevirtual 104 105 84 104 104 104 104 105 84 104 105 84 104 105 115 -1 
     [java]      | 61 
     [java]    51: enter       1 1 
     [java]      | 
     [java]    54: load_0      
     [java]      | 61 
     [java]    55: load_0      
     [java]      | 61 61 
     [java]    56: getfield    0 
     [java]      | 61 220 
     [java]    59: invokevirtual 104 105 -1 
     [java]      | 61 
     [java]   338: enter       1 1 
     [java]      | 
     [java]   341: const       107 
     [java]      | 107 
     [java]   346: const_1     
     [java]      | 107 1 
     [java]   347: bprint      k
     [java]      | 
     [java]   348: const       105 
     [java]      | 105 
     [java]   353: const_1     
     [java]      | 105 1 
     [java]   354: bprint      i
     [java]      | 
     [java]   355: const       10 
     [java]      | 10 
     [java]   360: const_1     
     [java]      | 10 1 
     [java]   361: bprint      
     [java] 
     [java]      | 
     [java]   362: exit        
     [java]      | 
     [java]   363: return      
     [java]      | 
     [java]    72: exit        
     [java]      | 
     [java]    73: return      
     [java]      | 
     [java]   478: exit        
     [java]      | 
     [java]   479: return      
     [java]      | 
     [java]  3890: read        
     [java]      | 20 
     [java]  3891: store       8 
     [java]      | 
     [java]  3893: const_0     
     [java]      | 0 
     [java]  3894: store_1     
     [java]      | 
     [java]  3895: load_0      
     [java]      | 2 
     [java]  3896: load_1      
     [java]      | 2 0 
     [java]  3897: aload       
     [java]      | 8 
     [java]  3898: load        8 
     [java]      | 8 20 
     [java]  3900: load_0      
     [java]      | 8 20 2 
     [java]  3901: load_1      
     [java]      | 8 20 2 0 
     [java]  3902: aload       
     [java]      | 8 20 8 
     [java]  3903: getfield    0 
     [java]      | 8 20 102 
     [java]  3906: invokevirtual 112 112 111 115 116 97 118 105 84 101 122 105 110 117 -1 
     [java]      | 8 20 
     [java]   238: enter       2 2 
     [java]      | 
     [java]   241: load_0      
     [java]      | 8 
     [java]   242: load_1      
     [java]      | 8 20 
     [java]   243: putfield    3 
     [java]      | 
     [java]   246: exit        
     [java]      | 
     [java]   247: return      
     [java]      | 
     [java]  3963: load_1      
     [java]      | 0 
     [java]  3964: pop         
     [java]      | 
     [java]  3965: inc         1 1 
     [java]      | 
     [java]  3968: load_1      
     [java]      | 1 
     [java]  3969: const       6 
     [java]      | 1 6 
     [java]  3974: jlt         -79 
     [java]      | 
     [java]  3895: load_0      
     [java]      | 2 
     [java]  3896: load_1      
     [java]      | 2 1 
     [java]  3897: aload       
     [java]      | 26 
     [java]  3898: load        8 
     [java]      | 26 20 
     [java]  3900: load_0      
     [java]      | 26 20 2 
     [java]  3901: load_1      
     [java]      | 26 20 2 1 
     [java]  3902: aload       
     [java]      | 26 20 26 
     [java]  3903: getfield    0 
     [java]      | 26 20 220 
     [java]  3906: invokevirtual 112 112 111 115 116 97 118 105 84 101 122 105 110 117 -1 
     [java]      | 26 20 
     [java]   364: enter       2 2 
     [java]      | 
     [java]   367: load_0      
     [java]      | 26 
     [java]   368: load_1      
     [java]      | 26 20 
     [java]   369: putfield    3 
     [java]      | 
     [java]   372: exit        
     [java]      | 
     [java]   373: return      
     [java]      | 
     [java]  3963: load_1      
     [java]      | 1 
     [java]  3964: pop         
     [java]      | 
     [java]  3965: inc         1 1 
     [java]      | 
     [java]  3968: load_1      
     [java]      | 2 
     [java]  3969: const       6 
     [java]      | 2 6 
     [java]  3974: jlt         -79 
     [java]      | 
     [java]  3895: load_0      
     [java]      | 2 
     [java]  3896: load_1      
     [java]      | 2 2 
     [java]  3897: aload       
     [java]      | 14 
     [java]  3898: load        8 
     [java]      | 14 20 
     [java]  3900: load_0      
     [java]      | 14 20 2 
     [java]  3901: load_1      
     [java]      | 14 20 2 2 
     [java]  3902: aload       
     [java]      | 14 20 14 
     [java]  3903: getfield    0 
     [java]      | 14 20 102 
     [java]  3906: invokevirtual 112 112 111 115 116 97 118 105 84 101 122 105 110 117 -1 
     [java]      | 14 20 
     [java]   238: enter       2 2 
     [java]      | 
     [java]   241: load_0      
     [java]      | 14 
     [java]   242: load_1      
     [java]      | 14 20 
     [java]   243: putfield    3 
     [java]      | 
     [java]   246: exit        
     [java]      | 
     [java]   247: return      
     [java]      | 
     [java]  3963: load_1      
     [java]      | 2 
     [java]  3964: pop         
     [java]      | 
     [java]  3965: inc         1 1 
     [java]      | 
     [java]  3968: load_1      
     [java]      | 3 
     [java]  3969: const       6 
     [java]      | 3 6 
     [java]  3974: jlt         -79 
     [java]      | 
     [java]  3895: load_0      
     [java]      | 2 
     [java]  3896: load_1      
     [java]      | 2 3 
     [java]  3897: aload       
     [java]      | 34 
     [java]  3898: load        8 
     [java]      | 34 20 
     [java]  3900: load_0      
     [java]      | 34 20 2 
     [java]  3901: load_1      
     [java]      | 34 20 2 3 
     [java]  3902: aload       
     [java]      | 34 20 34 
     [java]  3903: getfield    0 
     [java]      | 34 20 220 
     [java]  3906: invokevirtual 112 112 111 115 116 97 118 105 84 101 122 105 110 117 -1 
     [java]      | 34 20 
     [java]   364: enter       2 2 
     [java]      | 
     [java]   367: load_0      
     [java]      | 34 
     [java]   368: load_1      
     [java]      | 34 20 
     [java]   369: putfield    3 
     [java]      | 
     [java]   372: exit        
     [java]      | 
     [java]   373: return      
     [java]      | 
     [java]  3963: load_1      
     [java]      | 3 
     [java]  3964: pop         
     [java]      | 
     [java]  3965: inc         1 1 
     [java]      | 
     [java]  3968: load_1      
     [java]      | 4 
     [java]  3969: const       6 
     [java]      | 4 6 
     [java]  3974: jlt         -79 
     [java]      | 
     [java]  3895: load_0      
     [java]      | 2 
     [java]  3896: load_1      
     [java]      | 2 4 
     [java]  3897: aload       
     [java]      | 20 
     [java]  3898: load        8 
     [java]      | 20 20 
     [java]  3900: load_0      
     [java]      | 20 20 2 
     [java]  3901: load_1      
     [java]      | 20 20 2 4 
     [java]  3902: aload       
     [java]      | 20 20 20 
     [java]  3903: getfield    0 
     [java]      | 20 20 102 
     [java]  3906: invokevirtual 112 112 111 115 116 97 118 105 84 101 122 105 110 117 -1 
     [java]      | 20 20 
     [java]   238: enter       2 2 
     [java]      | 
     [java]   241: load_0      
     [java]      | 20 
     [java]   242: load_1      
     [java]      | 20 20 
     [java]   243: putfield    3 
     [java]      | 
     [java]   246: exit        
     [java]      | 
     [java]   247: return      
     [java]      | 
     [java]  3963: load_1      
     [java]      | 4 
     [java]  3964: pop         
     [java]      | 
     [java]  3965: inc         1 1 
     [java]      | 
     [java]  3968: load_1      
     [java]      | 5 
     [java]  3969: const       6 
     [java]      | 5 6 
     [java]  3974: jlt         -79 
     [java]      | 
     [java]  3895: load_0      
     [java]      | 2 
     [java]  3896: load_1      
     [java]      | 2 5 
     [java]  3897: aload       
     [java]      | 42 
     [java]  3898: load        8 
     [java]      | 42 20 
     [java]  3900: load_0      
     [java]      | 42 20 2 
     [java]  3901: load_1      
     [java]      | 42 20 2 5 
     [java]  3902: aload       
     [java]      | 42 20 42 
     [java]  3903: getfield    0 
     [java]      | 42 20 220 
     [java]  3906: invokevirtual 112 112 111 115 116 97 118 105 84 101 122 105 110 117 -1 
     [java]      | 42 20 
     [java]   364: enter       2 2 
     [java]      | 
     [java]   367: load_0      
     [java]      | 42 
     [java]   368: load_1      
     [java]      | 42 20 
     [java]   369: putfield    3 
     [java]      | 
     [java]   372: exit        
     [java]      | 
     [java]   373: return      
     [java]      | 
     [java]  3963: load_1      
     [java]      | 5 
     [java]  3964: pop         
     [java]      | 
     [java]  3965: inc         1 1 
     [java]      | 
     [java]  3968: load_1      
     [java]      | 6 
     [java]  3969: const       6 
     [java]      | 6 6 
     [java]  3974: jlt         -79 
     [java]      | 
     [java]  3977: const_0     
     [java]      | 0 
     [java]  3978: putstatic   1 
     [java]      | 
     [java]  3981: const_0     
     [java]      | 0 
     [java]  3982: putstatic   3 
     [java]      | 
     [java]  3985: const_1     
     [java]      | 1 
     [java]  3986: store_1     
     [java]      | 
     [java]  3987: load_1      
     [java]      | 1 
     [java]  3988: const_2     
     [java]      | 1 2 
     [java]  3989: rem         
     [java]      | 1 
     [java]  3990: const_0     
     [java]      | 1 0 
     [java]  3991: jne         11 
     [java]      | 
     [java]  4002: getstatic   1 
     [java]      | 0 
     [java]  4005: load_0      
     [java]      | 0 2 
     [java]  4006: load_1      
     [java]      | 0 2 1 
     [java]  4007: const_1     
     [java]      | 0 2 1 1 
     [java]  4008: sub         
     [java]      | 0 2 0 
     [java]  4009: aload       
     [java]      | 0 8 
     [java]  4010: load_0      
     [java]      | 0 8 2 
     [java]  4011: load_1      
     [java]      | 0 8 2 1 
     [java]  4012: const_1     
     [java]      | 0 8 2 1 1 
     [java]  4013: sub         
     [java]      | 0 8 2 0 
     [java]  4014: aload       
     [java]      | 0 8 8 
     [java]  4015: getfield    0 
     [java]      | 0 8 102 
     [java]  4018: invokevirtual 122 122 122 122 97 112 114 101 109 105 110 97 -1 
     [java]      | 0 8 
     [java]   321: enter       1 2 
     [java]      | 0 
     [java]   324: const_4     
     [java]      | 0 4 
     [java]   325: store_1     
     [java]      | 0 
     [java]   326: load_1      
     [java]      | 0 4 
     [java]   327: load_0      
     [java]      | 0 4 8 
     [java]   328: getfield    5 
     [java]      | 0 4 1 
     [java]   331: const_3     
     [java]      | 0 4 1 3 
     [java]   332: div         
     [java]      | 0 4 0 
     [java]   333: mul         
     [java]      | 0 0 
     [java]   334: exit        
     [java]      | 0 0 
     [java]   335: return      
     [java]      | 0 0 
     [java]  4059: add         
     [java]      | 0 
     [java]  4060: putstatic   1 
     [java]      | 
     [java]  4063: getstatic   3 
     [java]      | 0 
     [java]  4066: load_0      
     [java]      | 0 2 
     [java]  4067: load_1      
     [java]      | 0 2 1 
     [java]  4068: const_1     
     [java]      | 0 2 1 1 
     [java]  4069: sub         
     [java]      | 0 2 0 
     [java]  4070: aload       
     [java]      | 0 8 
     [java]  4071: load_0      
     [java]      | 0 8 2 
     [java]  4072: load_1      
     [java]      | 0 8 2 1 
     [java]  4073: const_1     
     [java]      | 0 8 2 1 1 
     [java]  4074: sub         
     [java]      | 0 8 2 0 
     [java]  4075: aload       
     [java]      | 0 8 8 
     [java]  4076: getfield    0 
     [java]      | 0 8 102 
     [java]  4079: invokevirtual 81 81 81 81 81 81 81 -1 
     [java]      | 0 8 
     [java]   102: enter       1 1 
     [java]      | 0 
     [java]   105: load_0      
     [java]      | 0 8 
     [java]   106: load_0      
     [java]      | 0 8 8 
     [java]   107: getfield    0 
     [java]      | 0 8 102 
     [java]   110: invokevirtual 122 122 122 122 97 112 114 101 109 105 110 97 -1 
     [java]      | 0 8 
     [java]   321: enter       1 2 
     [java]      | 0 
     [java]   324: const_4     
     [java]      | 0 4 
     [java]   325: store_1     
     [java]      | 0 
     [java]   326: load_1      
     [java]      | 0 4 
     [java]   327: load_0      
     [java]      | 0 4 8 
     [java]   328: getfield    5 
     [java]      | 0 4 1 
     [java]   331: const_3     
     [java]      | 0 4 1 3 
     [java]   332: div         
     [java]      | 0 4 0 
     [java]   333: mul         
     [java]      | 0 0 
     [java]   334: exit        
     [java]      | 0 0 
     [java]   335: return      
     [java]      | 0 0 
     [java]   151: load_0      
     [java]      | 0 0 8 
     [java]   152: getfield    3 
     [java]      | 0 0 20 
     [java]   155: mul         
     [java]      | 0 0 
     [java]   156: exit        
     [java]      | 0 0 
     [java]   157: return      
     [java]      | 0 0 
     [java]  4088: add         
     [java]      | 0 
     [java]  4089: putstatic   3 
     [java]      | 
     [java]  4092: load_0      
     [java]      | 2 
     [java]  4093: load_1      
     [java]      | 2 1 
     [java]  4094: const_1     
     [java]      | 2 1 1 
     [java]  4095: sub         
     [java]      | 2 0 
     [java]  4096: aload       
     [java]      | 8 
     [java]  4097: call        -3617 
     [java]      | 8 
     [java]   480: enter       1 1 
     [java]      | 
     [java]   483: load_0      
     [java]      | 8 
     [java]   484: load_0      
     [java]      | 8 8 
     [java]   485: getfield    0 
     [java]      | 8 102 
     [java]   488: invokevirtual 100 100 100 100 100 100 100 100 100 111 104 118 86 114 115 116 117 -1 
     [java]      | 8 
     [java]   170: enter       1 1 
     [java]      | 
     [java]   173: load_0      
     [java]      | 8 
     [java]   174: getfield    4 
     [java]      | 115 
     [java]   177: exit        
     [java]      | 115 
     [java]   178: return      
     [java]      | 115 
     [java]   529: const       115 
     [java]      | 115 115 
     [java]   534: jne         13 
     [java]      | 
     [java]   537: const       83 
     [java]      | 83 
     [java]   542: const_1     
     [java]      | 83 1 
     [java]   543: bprint      S
     [java]      | 
     [java]   544: jmp         64 
     [java]      | 
     [java]   608: const       10 
     [java]      | 10 
     [java]   613: const_1     
     [java]      | 10 1 
     [java]   614: bprint      
     [java] 
     [java]      | 
     [java]   615: load_0      
     [java]      | 8 
     [java]   616: load_0      
     [java]      | 8 8 
     [java]   617: getfield    0 
     [java]      | 8 102 
     [java]   620: invokevirtual 100 100 100 100 100 100 100 100 100 111 104 118 84 100 111 104 118 84 101 122 105 110 117 -1 
     [java]      | 8 
     [java]   181: enter       1 1 
     [java]      | 
     [java]   184: load_0      
     [java]      | 8 
     [java]   185: getfield    3 
     [java]      | 20 
     [java]   188: exit        
     [java]      | 20 
     [java]   189: return      
     [java]      | 20 
     [java]   665: const_5     
     [java]      | 20 5 
     [java]   666: print          20
     [java]      | 
     [java]   667: exit        
     [java]      | 
     [java]   668: return      
     [java]      | 
     [java]  4100: load_1      
     [java]      | 1 
     [java]  4101: pop         
     [java]      | 
     [java]  4102: inc         1 1 
     [java]      | 
     [java]  4105: load_1      
     [java]      | 2 
     [java]  4106: const       6 
     [java]      | 2 6 
     [java]  4111: jle         -124 
     [java]      | 
     [java]  3987: load_1      
     [java]      | 2 
     [java]  3988: const_2     
     [java]      | 2 2 
     [java]  3989: rem         
     [java]      | 0 
     [java]  3990: const_0     
     [java]      | 0 0 
     [java]  3991: jne         11 
     [java]      | 
     [java]  3994: load_1      
     [java]      | 2 
     [java]  3995: pop         
     [java]      | 
     [java]  3996: inc         1 1 
     [java]      | 
     [java]  3999: jmp         106 
     [java]      | 
     [java]  4105: load_1      
     [java]      | 3 
     [java]  4106: const       6 
     [java]      | 3 6 
     [java]  4111: jle         -124 
     [java]      | 
     [java]  3987: load_1      
     [java]      | 3 
     [java]  3988: const_2     
     [java]      | 3 2 
     [java]  3989: rem         
     [java]      | 1 
     [java]  3990: const_0     
     [java]      | 1 0 
     [java]  3991: jne         11 
     [java]      | 
     [java]  4002: getstatic   1 
     [java]      | 0 
     [java]  4005: load_0      
     [java]      | 0 2 
     [java]  4006: load_1      
     [java]      | 0 2 3 
     [java]  4007: const_1     
     [java]      | 0 2 3 1 
     [java]  4008: sub         
     [java]      | 0 2 2 
     [java]  4009: aload       
     [java]      | 0 14 
     [java]  4010: load_0      
     [java]      | 0 14 2 
     [java]  4011: load_1      
     [java]      | 0 14 2 3 
     [java]  4012: const_1     
     [java]      | 0 14 2 3 1 
     [java]  4013: sub         
     [java]      | 0 14 2 2 
     [java]  4014: aload       
     [java]      | 0 14 14 
     [java]  4015: getfield    0 
     [java]      | 0 14 102 
     [java]  4018: invokevirtual 122 122 122 122 97 112 114 101 109 105 110 97 -1 
     [java]      | 0 14 
     [java]   321: enter       1 2 
     [java]      | 0 
     [java]   324: const_4     
     [java]      | 0 4 
     [java]   325: store_1     
     [java]      | 0 
     [java]   326: load_1      
     [java]      | 0 4 
     [java]   327: load_0      
     [java]      | 0 4 14 
     [java]   328: getfield    5 
     [java]      | 0 4 2 
     [java]   331: const_3     
     [java]      | 0 4 2 3 
     [java]   332: div         
     [java]      | 0 4 0 
     [java]   333: mul         
     [java]      | 0 0 
     [java]   334: exit        
     [java]      | 0 0 
     [java]   335: return      
     [java]      | 0 0 
     [java]  4059: add         
     [java]      | 0 
     [java]  4060: putstatic   1 
     [java]      | 
     [java]  4063: getstatic   3 
     [java]      | 0 
     [java]  4066: load_0      
     [java]      | 0 2 
     [java]  4067: load_1      
     [java]      | 0 2 3 
     [java]  4068: const_1     
     [java]      | 0 2 3 1 
     [java]  4069: sub         
     [java]      | 0 2 2 
     [java]  4070: aload       
     [java]      | 0 14 
     [java]  4071: load_0      
     [java]      | 0 14 2 
     [java]  4072: load_1      
     [java]      | 0 14 2 3 
     [java]  4073: const_1     
     [java]      | 0 14 2 3 1 
     [java]  4074: sub         
     [java]      | 0 14 2 2 
     [java]  4075: aload       
     [java]      | 0 14 14 
     [java]  4076: getfield    0 
     [java]      | 0 14 102 
     [java]  4079: invokevirtual 81 81 81 81 81 81 81 -1 
     [java]      | 0 14 
     [java]   102: enter       1 1 
     [java]      | 0 
     [java]   105: load_0      
     [java]      | 0 14 
     [java]   106: load_0      
     [java]      | 0 14 14 
     [java]   107: getfield    0 
     [java]      | 0 14 102 
     [java]   110: invokevirtual 122 122 122 122 97 112 114 101 109 105 110 97 -1 
     [java]      | 0 14 
     [java]   321: enter       1 2 
     [java]      | 0 
     [java]   324: const_4     
     [java]      | 0 4 
     [java]   325: store_1     
     [java]      | 0 
     [java]   326: load_1      
     [java]      | 0 4 
     [java]   327: load_0      
     [java]      | 0 4 14 
     [java]   328: getfield    5 
     [java]      | 0 4 2 
     [java]   331: const_3     
     [java]      | 0 4 2 3 
     [java]   332: div         
     [java]      | 0 4 0 
     [java]   333: mul         
     [java]      | 0 0 
     [java]   334: exit        
     [java]      | 0 0 
     [java]   335: return      
     [java]      | 0 0 
     [java]   151: load_0      
     [java]      | 0 0 14 
     [java]   152: getfield    3 
     [java]      | 0 0 20 
     [java]   155: mul         
     [java]      | 0 0 
     [java]   156: exit        
     [java]      | 0 0 
     [java]   157: return      
     [java]      | 0 0 
     [java]  4088: add         
     [java]      | 0 
     [java]  4089: putstatic   3 
     [java]      | 
     [java]  4092: load_0      
     [java]      | 2 
     [java]  4093: load_1      
     [java]      | 2 3 
     [java]  4094: const_1     
     [java]      | 2 3 1 
     [java]  4095: sub         
     [java]      | 2 2 
     [java]  4096: aload       
     [java]      | 14 
     [java]  4097: call        -3617 
     [java]      | 14 
     [java]   480: enter       1 1 
     [java]      | 
     [java]   483: load_0      
     [java]      | 14 
     [java]   484: load_0      
     [java]      | 14 14 
     [java]   485: getfield    0 
     [java]      | 14 102 
     [java]   488: invokevirtual 100 100 100 100 100 100 100 100 100 111 104 118 86 114 115 116 117 -1 
     [java]      | 14 
     [java]   170: enter       1 1 
     [java]      | 
     [java]   173: load_0      
     [java]      | 14 
     [java]   174: getfield    4 
     [java]      | 115 
     [java]   177: exit        
     [java]      | 115 
     [java]   178: return      
     [java]      | 115 
     [java]   529: const       115 
     [java]      | 115 115 
     [java]   534: jne         13 
     [java]      | 
     [java]   537: const       83 
     [java]      | 83 
     [java]   542: const_1     
     [java]      | 83 1 
     [java]   543: bprint      S
     [java]      | 
     [java]   544: jmp         64 
     [java]      | 
     [java]   608: const       10 
     [java]      | 10 
     [java]   613: const_1     
     [java]      | 10 1 
     [java]   614: bprint      
     [java] 
     [java]      | 
     [java]   615: load_0      
     [java]      | 14 
     [java]   616: load_0      
     [java]      | 14 14 
     [java]   617: getfield    0 
     [java]      | 14 102 
     [java]   620: invokevirtual 100 100 100 100 100 100 100 100 100 111 104 118 84 100 111 104 118 84 101 122 105 110 117 -1 
     [java]      | 14 
     [java]   181: enter       1 1 
     [java]      | 
     [java]   184: load_0      
     [java]      | 14 
     [java]   185: getfield    3 
     [java]      | 20 
     [java]   188: exit        
     [java]      | 20 
     [java]   189: return      
     [java]      | 20 
     [java]   665: const_5     
     [java]      | 20 5 
     [java]   666: print          20
     [java]      | 
     [java]   667: exit        
     [java]      | 
     [java]   668: return      
     [java]      | 
     [java]  4100: load_1      
     [java]      | 3 
     [java]  4101: pop         
     [java]      | 
     [java]  4102: inc         1 1 
     [java]      | 
     [java]  4105: load_1      
     [java]      | 4 
     [java]  4106: const       6 
     [java]      | 4 6 
     [java]  4111: jle         -124 
     [java]      | 
     [java]  3987: load_1      
     [java]      | 4 
     [java]  3988: const_2     
     [java]      | 4 2 
     [java]  3989: rem         
     [java]      | 0 
     [java]  3990: const_0     
     [java]      | 0 0 
     [java]  3991: jne         11 
     [java]      | 
     [java]  3994: load_1      
     [java]      | 4 
     [java]  3995: pop         
     [java]      | 
     [java]  3996: inc         1 1 
     [java]      | 
     [java]  3999: jmp         106 
     [java]      | 
     [java]  4105: load_1      
     [java]      | 5 
     [java]  4106: const       6 
     [java]      | 5 6 
     [java]  4111: jle         -124 
     [java]      | 
     [java]  3987: load_1      
     [java]      | 5 
     [java]  3988: const_2     
     [java]      | 5 2 
     [java]  3989: rem         
     [java]      | 1 
     [java]  3990: const_0     
     [java]      | 1 0 
     [java]  3991: jne         11 
     [java]      | 
     [java]  4002: getstatic   1 
     [java]      | 0 
     [java]  4005: load_0      
     [java]      | 0 2 
     [java]  4006: load_1      
     [java]      | 0 2 5 
     [java]  4007: const_1     
     [java]      | 0 2 5 1 
     [java]  4008: sub         
     [java]      | 0 2 4 
     [java]  4009: aload       
     [java]      | 0 20 
     [java]  4010: load_0      
     [java]      | 0 20 2 
     [java]  4011: load_1      
     [java]      | 0 20 2 5 
     [java]  4012: const_1     
     [java]      | 0 20 2 5 1 
     [java]  4013: sub         
     [java]      | 0 20 2 4 
     [java]  4014: aload       
     [java]      | 0 20 20 
     [java]  4015: getfield    0 
     [java]      | 0 20 102 
     [java]  4018: invokevirtual 122 122 122 122 97 112 114 101 109 105 110 97 -1 
     [java]      | 0 20 
     [java]   321: enter       1 2 
     [java]      | 0 
     [java]   324: const_4     
     [java]      | 0 4 
     [java]   325: store_1     
     [java]      | 0 
     [java]   326: load_1      
     [java]      | 0 4 
     [java]   327: load_0      
     [java]      | 0 4 20 
     [java]   328: getfield    5 
     [java]      | 0 4 3 
     [java]   331: const_3     
     [java]      | 0 4 3 3 
     [java]   332: div         
     [java]      | 0 4 1 
     [java]   333: mul         
     [java]      | 0 4 
     [java]   334: exit        
     [java]      | 0 4 
     [java]   335: return      
     [java]      | 0 4 
     [java]  4059: add         
     [java]      | 4 
     [java]  4060: putstatic   1 
     [java]      | 
     [java]  4063: getstatic   3 
     [java]      | 0 
     [java]  4066: load_0      
     [java]      | 0 2 
     [java]  4067: load_1      
     [java]      | 0 2 5 
     [java]  4068: const_1     
     [java]      | 0 2 5 1 
     [java]  4069: sub         
     [java]      | 0 2 4 
     [java]  4070: aload       
     [java]      | 0 20 
     [java]  4071: load_0      
     [java]      | 0 20 2 
     [java]  4072: load_1      
     [java]      | 0 20 2 5 
     [java]  4073: const_1     
     [java]      | 0 20 2 5 1 
     [java]  4074: sub         
     [java]      | 0 20 2 4 
     [java]  4075: aload       
     [java]      | 0 20 20 
     [java]  4076: getfield    0 
     [java]      | 0 20 102 
     [java]  4079: invokevirtual 81 81 81 81 81 81 81 -1 
     [java]      | 0 20 
     [java]   102: enter       1 1 
     [java]      | 0 
     [java]   105: load_0      
     [java]      | 0 20 
     [java]   106: load_0      
     [java]      | 0 20 20 
     [java]   107: getfield    0 
     [java]      | 0 20 102 
     [java]   110: invokevirtual 122 122 122 122 97 112 114 101 109 105 110 97 -1 
     [java]      | 0 20 
     [java]   321: enter       1 2 
     [java]      | 0 
     [java]   324: const_4     
     [java]      | 0 4 
     [java]   325: store_1     
     [java]      | 0 
     [java]   326: load_1      
     [java]      | 0 4 
     [java]   327: load_0      
     [java]      | 0 4 20 
     [java]   328: getfield    5 
     [java]      | 0 4 3 
     [java]   331: const_3     
     [java]      | 0 4 3 3 
     [java]   332: div         
     [java]      | 0 4 1 
     [java]   333: mul         
     [java]      | 0 4 
     [java]   334: exit        
     [java]      | 0 4 
     [java]   335: return      
     [java]      | 0 4 
     [java]   151: load_0      
     [java]      | 0 4 20 
     [java]   152: getfield    3 
     [java]      | 0 4 20 
     [java]   155: mul         
     [java]      | 0 80 
     [java]   156: exit        
     [java]      | 0 80 
     [java]   157: return      
     [java]      | 0 80 
     [java]  4088: add         
     [java]      | 80 
     [java]  4089: putstatic   3 
     [java]      | 
     [java]  4092: load_0      
     [java]      | 2 
     [java]  4093: load_1      
     [java]      | 2 5 
     [java]  4094: const_1     
     [java]      | 2 5 1 
     [java]  4095: sub         
     [java]      | 2 4 
     [java]  4096: aload       
     [java]      | 20 
     [java]  4097: call        -3617 
     [java]      | 20 
     [java]   480: enter       1 1 
     [java]      | 
     [java]   483: load_0      
     [java]      | 20 
     [java]   484: load_0      
     [java]      | 20 20 
     [java]   485: getfield    0 
     [java]      | 20 102 
     [java]   488: invokevirtual 100 100 100 100 100 100 100 100 100 111 104 118 86 114 115 116 117 -1 
     [java]      | 20 
     [java]   170: enter       1 1 
     [java]      | 
     [java]   173: load_0      
     [java]      | 20 
     [java]   174: getfield    4 
     [java]      | 115 
     [java]   177: exit        
     [java]      | 115 
     [java]   178: return      
     [java]      | 115 
     [java]   529: const       115 
     [java]      | 115 115 
     [java]   534: jne         13 
     [java]      | 
     [java]   537: const       83 
     [java]      | 83 
     [java]   542: const_1     
     [java]      | 83 1 
     [java]   543: bprint      S
     [java]      | 
     [java]   544: jmp         64 
     [java]      | 
     [java]   608: const       10 
     [java]      | 10 
     [java]   613: const_1     
     [java]      | 10 1 
     [java]   614: bprint      
     [java] 
     [java]      | 
     [java]   615: load_0      
     [java]      | 20 
     [java]   616: load_0      
     [java]      | 20 20 
     [java]   617: getfield    0 
     [java]      | 20 102 
     [java]   620: invokevirtual 100 100 100 100 100 100 100 100 100 111 104 118 84 100 111 104 118 84 101 122 105 110 117 -1 
     [java]      | 20 
     [java]   181: enter       1 1 
     [java]      | 
     [java]   184: load_0      
     [java]      | 20 
     [java]   185: getfield    3 
     [java]      | 20 
     [java]   188: exit        
     [java]      | 20 
     [java]   189: return      
     [java]      | 20 
     [java]   665: const_5     
     [java]      | 20 5 
     [java]   666: print          20
     [java]      | 
     [java]   667: exit        
     [java]      | 
     [java]   668: return      
     [java]      | 
     [java]  4100: load_1      
     [java]      | 5 
     [java]  4101: pop         
     [java]      | 
     [java]  4102: inc         1 1 
     [java]      | 
     [java]  4105: load_1      
     [java]      | 6 
     [java]  4106: const       6 
     [java]      | 6 6 
     [java]  4111: jle         -124 
     [java]      | 
     [java]  3987: load_1      
     [java]      | 6 
     [java]  3988: const_2     
     [java]      | 6 2 
     [java]  3989: rem         
     [java]      | 0 
     [java]  3990: const_0     
     [java]      | 0 0 
     [java]  3991: jne         11 
     [java]      | 
     [java]  3994: load_1      
     [java]      | 6 
     [java]  3995: pop         
     [java]      | 
     [java]  3996: inc         1 1 
     [java]      | 
     [java]  3999: jmp         106 
     [java]      | 
     [java]  4105: load_1      
     [java]      | 7 
     [java]  4106: const       6 
     [java]      | 7 6 
     [java]  4111: jle         -124 
     [java]      | 
     [java]  4114: const_0     
     [java]      | 0 
     [java]  4115: putstatic   0 
     [java]      | 
     [java]  4118: const_0     
     [java]      | 0 
     [java]  4119: putstatic   2 
     [java]      | 
     [java]  4122: const_1     
     [java]      | 1 
     [java]  4123: store_1     
     [java]      | 
     [java]  4124: load_1      
     [java]      | 1 
     [java]  4125: const_2     
     [java]      | 1 2 
     [java]  4126: rem         
     [java]      | 1 
     [java]  4127: const_1     
     [java]      | 1 1 
     [java]  4128: jne         11 
     [java]      | 
     [java]  4131: load_1      
     [java]      | 1 
     [java]  4132: pop         
     [java]      | 
     [java]  4133: inc         1 1 
     [java]      | 
     [java]  4136: jmp         106 
     [java]      | 
     [java]  4242: load_1      
     [java]      | 2 
     [java]  4243: const       6 
     [java]      | 2 6 
     [java]  4248: jle         -124 
     [java]      | 
     [java]  4124: load_1      
     [java]      | 2 
     [java]  4125: const_2     
     [java]      | 2 2 
     [java]  4126: rem         
     [java]      | 0 
     [java]  4127: const_1     
     [java]      | 0 1 
     [java]  4128: jne         11 
     [java]      | 
     [java]  4139: getstatic   0 
     [java]      | 0 
     [java]  4142: load_0      
     [java]      | 0 2 
     [java]  4143: load_1      
     [java]      | 0 2 2 
     [java]  4144: const_1     
     [java]      | 0 2 2 1 
     [java]  4145: sub         
     [java]      | 0 2 1 
     [java]  4146: aload       
     [java]      | 0 26 
     [java]  4147: load_0      
     [java]      | 0 26 2 
     [java]  4148: load_1      
     [java]      | 0 26 2 2 
     [java]  4149: const_1     
     [java]      | 0 26 2 2 1 
     [java]  4150: sub         
     [java]      | 0 26 2 1 
     [java]  4151: aload       
     [java]      | 0 26 26 
     [java]  4152: getfield    0 
     [java]      | 0 26 220 
     [java]  4155: invokevirtual 122 122 122 122 97 112 114 101 109 105 110 97 -1 
     [java]      | 0 26 
     [java]   403: enter       1 2 
     [java]      | 0 
     [java]   406: load_0      
     [java]      | 0 26 
     [java]   407: getfield    5 
     [java]      | 0 1 
     [java]   410: load_0      
     [java]      | 0 1 26 
     [java]   411: getfield    6 
     [java]      | 0 1 2 
     [java]   414: mul         
     [java]      | 0 2 
     [java]   415: load_0      
     [java]      | 0 2 26 
     [java]   416: getfield    7 
     [java]      | 0 2 3 
     [java]   419: mul         
     [java]      | 0 6 
     [java]   420: store_1     
     [java]      | 0 
     [java]   421: load_1      
     [java]      | 0 6 
     [java]   422: exit        
     [java]      | 0 6 
     [java]   423: return      
     [java]      | 0 6 
     [java]  4196: add         
     [java]      | 6 
     [java]  4197: putstatic   0 
     [java]      | 
     [java]  4200: getstatic   2 
     [java]      | 0 
     [java]  4203: load_0      
     [java]      | 0 2 
     [java]  4204: load_1      
     [java]      | 0 2 2 
     [java]  4205: const_1     
     [java]      | 0 2 2 1 
     [java]  4206: sub         
     [java]      | 0 2 1 
     [java]  4207: aload       
     [java]      | 0 26 
     [java]  4208: load_0      
     [java]      | 0 26 2 
     [java]  4209: load_1      
     [java]      | 0 26 2 2 
     [java]  4210: const_1     
     [java]      | 0 26 2 2 1 
     [java]  4211: sub         
     [java]      | 0 26 2 1 
     [java]  4212: aload       
     [java]      | 0 26 26 
     [java]  4213: getfield    0 
     [java]      | 0 26 220 
     [java]  4216: invokevirtual 81 81 81 81 81 81 81 81 -1 
     [java]      | 0 26 
     [java]   102: enter       1 1 
     [java]      | 0 
     [java]   105: load_0      
     [java]      | 0 26 
     [java]   106: load_0      
     [java]      | 0 26 26 
     [java]   107: getfield    0 
     [java]      | 0 26 220 
     [java]   110: invokevirtual 122 122 122 122 97 112 114 101 109 105 110 97 -1 
     [java]      | 0 26 
     [java]   403: enter       1 2 
     [java]      | 0 
     [java]   406: load_0      
     [java]      | 0 26 
     [java]   407: getfield    5 
     [java]      | 0 1 
     [java]   410: load_0      
     [java]      | 0 1 26 
     [java]   411: getfield    6 
     [java]      | 0 1 2 
     [java]   414: mul         
     [java]      | 0 2 
     [java]   415: load_0      
     [java]      | 0 2 26 
     [java]   416: getfield    7 
     [java]      | 0 2 3 
     [java]   419: mul         
     [java]      | 0 6 
     [java]   420: store_1     
     [java]      | 0 
     [java]   421: load_1      
     [java]      | 0 6 
     [java]   422: exit        
     [java]      | 0 6 
     [java]   423: return      
     [java]      | 0 6 
     [java]   151: load_0      
     [java]      | 0 6 26 
     [java]   152: getfield    3 
     [java]      | 0 6 20 
     [java]   155: mul         
     [java]      | 0 120 
     [java]   156: exit        
     [java]      | 0 120 
     [java]   157: return      
     [java]      | 0 120 
     [java]  4225: add         
     [java]      | 120 
     [java]  4226: putstatic   2 
     [java]      | 
     [java]  4229: load_0      
     [java]      | 2 
     [java]  4230: load_1      
     [java]      | 2 2 
     [java]  4231: const_1     
     [java]      | 2 2 1 
     [java]  4232: sub         
     [java]      | 2 1 
     [java]  4233: aload       
     [java]      | 26 
     [java]  4234: call        -3754 
     [java]      | 26 
     [java]   480: enter       1 1 
     [java]      | 
     [java]   483: load_0      
     [java]      | 26 
     [java]   484: load_0      
     [java]      | 26 26 
     [java]   485: getfield    0 
     [java]      | 26 220 
     [java]   488: invokevirtual 100 100 100 100 100 100 100 100 100 100 111 104 118 86 114 115 116 117 -1 
     [java]      | 26 
     [java]   170: enter       1 1 
     [java]      | 
     [java]   173: load_0      
     [java]      | 26 
     [java]   174: getfield    4 
     [java]      | 107 
     [java]   177: exit        
     [java]      | 107 
     [java]   178: return      
     [java]      | 107 
     [java]   529: const       115 
     [java]      | 107 115 
     [java]   534: jne         13 
     [java]      | 
     [java]   547: load_0      
     [java]      | 26 
     [java]   548: load_0      
     [java]      | 26 26 
     [java]   549: getfield    0 
     [java]      | 26 220 
     [java]   552: invokevirtual 100 100 100 100 100 100 100 100 100 100 111 104 118 86 114 115 116 117 -1 
     [java]      | 26 
     [java]   170: enter       1 1 
     [java]      | 
     [java]   173: load_0      
     [java]      | 26 
     [java]   174: getfield    4 
     [java]      | 107 
     [java]   177: exit        
     [java]      | 107 
     [java]   178: return      
     [java]      | 107 
     [java]   593: const       107 
     [java]      | 107 107 
     [java]   598: jne         10 
     [java]      | 
     [java]   601: const       75 
     [java]      | 75 
     [java]   606: const_1     
     [java]      | 75 1 
     [java]   607: bprint      K
     [java]      | 
     [java]   608: const       10 
     [java]      | 10 
     [java]   613: const_1     
     [java]      | 10 1 
     [java]   614: bprint      
     [java] 
     [java]      | 
     [java]   615: load_0      
     [java]      | 26 
     [java]   616: load_0      
     [java]      | 26 26 
     [java]   617: getfield    0 
     [java]      | 26 220 
     [java]   620: invokevirtual 100 100 100 100 100 100 100 100 100 100 111 104 118 84 100 111 104 118 84 101 122 105 110 117 -1 
     [java]      | 26 
     [java]   181: enter       1 1 
     [java]      | 
     [java]   184: load_0      
     [java]      | 26 
     [java]   185: getfield    3 
     [java]      | 20 
     [java]   188: exit        
     [java]      | 20 
     [java]   189: return      
     [java]      | 20 
     [java]   665: const_5     
     [java]      | 20 5 
     [java]   666: print          20
     [java]      | 
     [java]   667: exit        
     [java]      | 
     [java]   668: return      
     [java]      | 
     [java]  4237: load_1      
     [java]      | 2 
     [java]  4238: pop         
     [java]      | 
     [java]  4239: inc         1 1 
     [java]      | 
     [java]  4242: load_1      
     [java]      | 3 
     [java]  4243: const       6 
     [java]      | 3 6 
     [java]  4248: jle         -124 
     [java]      | 
     [java]  4124: load_1      
     [java]      | 3 
     [java]  4125: const_2     
     [java]      | 3 2 
     [java]  4126: rem         
     [java]      | 1 
     [java]  4127: const_1     
     [java]      | 1 1 
     [java]  4128: jne         11 
     [java]      | 
     [java]  4131: load_1      
     [java]      | 3 
     [java]  4132: pop         
     [java]      | 
     [java]  4133: inc         1 1 
     [java]      | 
     [java]  4136: jmp         106 
     [java]      | 
     [java]  4242: load_1      
     [java]      | 4 
     [java]  4243: const       6 
     [java]      | 4 6 
     [java]  4248: jle         -124 
     [java]      | 
     [java]  4124: load_1      
     [java]      | 4 
     [java]  4125: const_2     
     [java]      | 4 2 
     [java]  4126: rem         
     [java]      | 0 
     [java]  4127: const_1     
     [java]      | 0 1 
     [java]  4128: jne         11 
     [java]      | 
     [java]  4139: getstatic   0 
     [java]      | 6 
     [java]  4142: load_0      
     [java]      | 6 2 
     [java]  4143: load_1      
     [java]      | 6 2 4 
     [java]  4144: const_1     
     [java]      | 6 2 4 1 
     [java]  4145: sub         
     [java]      | 6 2 3 
     [java]  4146: aload       
     [java]      | 6 34 
     [java]  4147: load_0      
     [java]      | 6 34 2 
     [java]  4148: load_1      
     [java]      | 6 34 2 4 
     [java]  4149: const_1     
     [java]      | 6 34 2 4 1 
     [java]  4150: sub         
     [java]      | 6 34 2 3 
     [java]  4151: aload       
     [java]      | 6 34 34 
     [java]  4152: getfield    0 
     [java]      | 6 34 220 
     [java]  4155: invokevirtual 122 122 122 122 97 112 114 101 109 105 110 97 -1 
     [java]      | 6 34 
     [java]   403: enter       1 2 
     [java]      | 6 
     [java]   406: load_0      
     [java]      | 6 34 
     [java]   407: getfield    5 
     [java]      | 6 2 
     [java]   410: load_0      
     [java]      | 6 2 34 
     [java]   411: getfield    6 
     [java]      | 6 2 3 
     [java]   414: mul         
     [java]      | 6 6 
     [java]   415: load_0      
     [java]      | 6 6 34 
     [java]   416: getfield    7 
     [java]      | 6 6 4 
     [java]   419: mul         
     [java]      | 6 24 
     [java]   420: store_1     
     [java]      | 6 
     [java]   421: load_1      
     [java]      | 6 24 
     [java]   422: exit        
     [java]      | 6 24 
     [java]   423: return      
     [java]      | 6 24 
     [java]  4196: add         
     [java]      | 30 
     [java]  4197: putstatic   0 
     [java]      | 
     [java]  4200: getstatic   2 
     [java]      | 120 
     [java]  4203: load_0      
     [java]      | 120 2 
     [java]  4204: load_1      
     [java]      | 120 2 4 
     [java]  4205: const_1     
     [java]      | 120 2 4 1 
     [java]  4206: sub         
     [java]      | 120 2 3 
     [java]  4207: aload       
     [java]      | 120 34 
     [java]  4208: load_0      
     [java]      | 120 34 2 
     [java]  4209: load_1      
     [java]      | 120 34 2 4 
     [java]  4210: const_1     
     [java]      | 120 34 2 4 1 
     [java]  4211: sub         
     [java]      | 120 34 2 3 
     [java]  4212: aload       
     [java]      | 120 34 34 
     [java]  4213: getfield    0 
     [java]      | 120 34 220 
     [java]  4216: invokevirtual 81 81 81 81 81 81 81 81 -1 
     [java]      | 120 34 
     [java]   102: enter       1 1 
     [java]      | 120 
     [java]   105: load_0      
     [java]      | 120 34 
     [java]   106: load_0      
     [java]      | 120 34 34 
     [java]   107: getfield    0 
     [java]      | 120 34 220 
     [java]   110: invokevirtual 122 122 122 122 97 112 114 101 109 105 110 97 -1 
     [java]      | 120 34 
     [java]   403: enter       1 2 
     [java]      | 120 
     [java]   406: load_0      
     [java]      | 120 34 
     [java]   407: getfield    5 
     [java]      | 120 2 
     [java]   410: load_0      
     [java]      | 120 2 34 
     [java]   411: getfield    6 
     [java]      | 120 2 3 
     [java]   414: mul         
     [java]      | 120 6 
     [java]   415: load_0      
     [java]      | 120 6 34 
     [java]   416: getfield    7 
     [java]      | 120 6 4 
     [java]   419: mul         
     [java]      | 120 24 
     [java]   420: store_1     
     [java]      | 120 
     [java]   421: load_1      
     [java]      | 120 24 
     [java]   422: exit        
     [java]      | 120 24 
     [java]   423: return      
     [java]      | 120 24 
     [java]   151: load_0      
     [java]      | 120 24 34 
     [java]   152: getfield    3 
     [java]      | 120 24 20 
     [java]   155: mul         
     [java]      | 120 480 
     [java]   156: exit        
     [java]      | 120 480 
     [java]   157: return      
     [java]      | 120 480 
     [java]  4225: add         
     [java]      | 600 
     [java]  4226: putstatic   2 
     [java]      | 
     [java]  4229: load_0      
     [java]      | 2 
     [java]  4230: load_1      
     [java]      | 2 4 
     [java]  4231: const_1     
     [java]      | 2 4 1 
     [java]  4232: sub         
     [java]      | 2 3 
     [java]  4233: aload       
     [java]      | 34 
     [java]  4234: call        -3754 
     [java]      | 34 
     [java]   480: enter       1 1 
     [java]      | 
     [java]   483: load_0      
     [java]      | 34 
     [java]   484: load_0      
     [java]      | 34 34 
     [java]   485: getfield    0 
     [java]      | 34 220 
     [java]   488: invokevirtual 100 100 100 100 100 100 100 100 100 100 111 104 118 86 114 115 116 117 -1 
     [java]      | 34 
     [java]   170: enter       1 1 
     [java]      | 
     [java]   173: load_0      
     [java]      | 34 
     [java]   174: getfield    4 
     [java]      | 107 
     [java]   177: exit        
     [java]      | 107 
     [java]   178: return      
     [java]      | 107 
     [java]   529: const       115 
     [java]      | 107 115 
     [java]   534: jne         13 
     [java]      | 
     [java]   547: load_0      
     [java]      | 34 
     [java]   548: load_0      
     [java]      | 34 34 
     [java]   549: getfield    0 
     [java]      | 34 220 
     [java]   552: invokevirtual 100 100 100 100 100 100 100 100 100 100 111 104 118 86 114 115 116 117 -1 
     [java]      | 34 
     [java]   170: enter       1 1 
     [java]      | 
     [java]   173: load_0      
     [java]      | 34 
     [java]   174: getfield    4 
     [java]      | 107 
     [java]   177: exit        
     [java]      | 107 
     [java]   178: return      
     [java]      | 107 
     [java]   593: const       107 
     [java]      | 107 107 
     [java]   598: jne         10 
     [java]      | 
     [java]   601: const       75 
     [java]      | 75 
     [java]   606: const_1     
     [java]      | 75 1 
     [java]   607: bprint      K
     [java]      | 
     [java]   608: const       10 
     [java]      | 10 
     [java]   613: const_1     
     [java]      | 10 1 
     [java]   614: bprint      
     [java] 
     [java]      | 
     [java]   615: load_0      
     [java]      | 34 
     [java]   616: load_0      
     [java]      | 34 34 
     [java]   617: getfield    0 
     [java]      | 34 220 
     [java]   620: invokevirtual 100 100 100 100 100 100 100 100 100 100 111 104 118 84 100 111 104 118 84 101 122 105 110 117 -1 
     [java]      | 34 
     [java]   181: enter       1 1 
     [java]      | 
     [java]   184: load_0      
     [java]      | 34 
     [java]   185: getfield    3 
     [java]      | 20 
     [java]   188: exit        
     [java]      | 20 
     [java]   189: return      
     [java]      | 20 
     [java]   665: const_5     
     [java]      | 20 5 
     [java]   666: print          20
     [java]      | 
     [java]   667: exit        
     [java]      | 
     [java]   668: return      
     [java]      | 
     [java]  4237: load_1      
     [java]      | 4 
     [java]  4238: pop         
     [java]      | 
     [java]  4239: inc         1 1 
     [java]      | 
     [java]  4242: load_1      
     [java]      | 5 
     [java]  4243: const       6 
     [java]      | 5 6 
     [java]  4248: jle         -124 
     [java]      | 
     [java]  4124: load_1      
     [java]      | 5 
     [java]  4125: const_2     
     [java]      | 5 2 
     [java]  4126: rem         
     [java]      | 1 
     [java]  4127: const_1     
     [java]      | 1 1 
     [java]  4128: jne         11 
     [java]      | 
     [java]  4131: load_1      
     [java]      | 5 
     [java]  4132: pop         
     [java]      | 
     [java]  4133: inc         1 1 
     [java]      | 
     [java]  4136: jmp         106 
     [java]      | 
     [java]  4242: load_1      
     [java]      | 6 
     [java]  4243: const       6 
     [java]      | 6 6 
     [java]  4248: jle         -124 
     [java]      | 
     [java]  4124: load_1      
     [java]      | 6 
     [java]  4125: const_2     
     [java]      | 6 2 
     [java]  4126: rem         
     [java]      | 0 
     [java]  4127: const_1     
     [java]      | 0 1 
     [java]  4128: jne         11 
     [java]      | 
     [java]  4139: getstatic   0 
     [java]      | 30 
     [java]  4142: load_0      
     [java]      | 30 2 
     [java]  4143: load_1      
     [java]      | 30 2 6 
     [java]  4144: const_1     
     [java]      | 30 2 6 1 
     [java]  4145: sub         
     [java]      | 30 2 5 
     [java]  4146: aload       
     [java]      | 30 42 
     [java]  4147: load_0      
     [java]      | 30 42 2 
     [java]  4148: load_1      
     [java]      | 30 42 2 6 
     [java]  4149: const_1     
     [java]      | 30 42 2 6 1 
     [java]  4150: sub         
     [java]      | 30 42 2 5 
     [java]  4151: aload       
     [java]      | 30 42 42 
     [java]  4152: getfield    0 
     [java]      | 30 42 220 
     [java]  4155: invokevirtual 122 122 122 122 97 112 114 101 109 105 110 97 -1 
     [java]      | 30 42 
     [java]   403: enter       1 2 
     [java]      | 30 
     [java]   406: load_0      
     [java]      | 30 42 
     [java]   407: getfield    5 
     [java]      | 30 3 
     [java]   410: load_0      
     [java]      | 30 3 42 
     [java]   411: getfield    6 
     [java]      | 30 3 4 
     [java]   414: mul         
     [java]      | 30 12 
     [java]   415: load_0      
     [java]      | 30 12 42 
     [java]   416: getfield    7 
     [java]      | 30 12 5 
     [java]   419: mul         
     [java]      | 30 60 
     [java]   420: store_1     
     [java]      | 30 
     [java]   421: load_1      
     [java]      | 30 60 
     [java]   422: exit        
     [java]      | 30 60 
     [java]   423: return      
     [java]      | 30 60 
     [java]  4196: add         
     [java]      | 90 
     [java]  4197: putstatic   0 
     [java]      | 
     [java]  4200: getstatic   2 
     [java]      | 600 
     [java]  4203: load_0      
     [java]      | 600 2 
     [java]  4204: load_1      
     [java]      | 600 2 6 
     [java]  4205: const_1     
     [java]      | 600 2 6 1 
     [java]  4206: sub         
     [java]      | 600 2 5 
     [java]  4207: aload       
     [java]      | 600 42 
     [java]  4208: load_0      
     [java]      | 600 42 2 
     [java]  4209: load_1      
     [java]      | 600 42 2 6 
     [java]  4210: const_1     
     [java]      | 600 42 2 6 1 
     [java]  4211: sub         
     [java]      | 600 42 2 5 
     [java]  4212: aload       
     [java]      | 600 42 42 
     [java]  4213: getfield    0 
     [java]      | 600 42 220 
     [java]  4216: invokevirtual 81 81 81 81 81 81 81 81 -1 
     [java]      | 600 42 
     [java]   102: enter       1 1 
     [java]      | 600 
     [java]   105: load_0      
     [java]      | 600 42 
     [java]   106: load_0      
     [java]      | 600 42 42 
     [java]   107: getfield    0 
     [java]      | 600 42 220 
     [java]   110: invokevirtual 122 122 122 122 97 112 114 101 109 105 110 97 -1 
     [java]      | 600 42 
     [java]   403: enter       1 2 
     [java]      | 600 
     [java]   406: load_0      
     [java]      | 600 42 
     [java]   407: getfield    5 
     [java]      | 600 3 
     [java]   410: load_0      
     [java]      | 600 3 42 
     [java]   411: getfield    6 
     [java]      | 600 3 4 
     [java]   414: mul         
     [java]      | 600 12 
     [java]   415: load_0      
     [java]      | 600 12 42 
     [java]   416: getfield    7 
     [java]      | 600 12 5 
     [java]   419: mul         
     [java]      | 600 60 
     [java]   420: store_1     
     [java]      | 600 
     [java]   421: load_1      
     [java]      | 600 60 
     [java]   422: exit        
     [java]      | 600 60 
     [java]   423: return      
     [java]      | 600 60 
     [java]   151: load_0      
     [java]      | 600 60 42 
     [java]   152: getfield    3 
     [java]      | 600 60 20 
     [java]   155: mul         
     [java]      | 600 1200 
     [java]   156: exit        
     [java]      | 600 1200 
     [java]   157: return      
     [java]      | 600 1200 
     [java]  4225: add         
     [java]      | 1800 
     [java]  4226: putstatic   2 
     [java]      | 
     [java]  4229: load_0      
     [java]      | 2 
     [java]  4230: load_1      
     [java]      | 2 6 
     [java]  4231: const_1     
     [java]      | 2 6 1 
     [java]  4232: sub         
     [java]      | 2 5 
     [java]  4233: aload       
     [java]      | 42 
     [java]  4234: call        -3754 
     [java]      | 42 
     [java]   480: enter       1 1 
     [java]      | 
     [java]   483: load_0      
     [java]      | 42 
     [java]   484: load_0      
     [java]      | 42 42 
     [java]   485: getfield    0 
     [java]      | 42 220 
     [java]   488: invokevirtual 100 100 100 100 100 100 100 100 100 100 111 104 118 86 114 115 116 117 -1 
     [java]      | 42 
     [java]   170: enter       1 1 
     [java]      | 
     [java]   173: load_0      
     [java]      | 42 
     [java]   174: getfield    4 
     [java]      | 107 
     [java]   177: exit        
     [java]      | 107 
     [java]   178: return      
     [java]      | 107 
     [java]   529: const       115 
     [java]      | 107 115 
     [java]   534: jne         13 
     [java]      | 
     [java]   547: load_0      
     [java]      | 42 
     [java]   548: load_0      
     [java]      | 42 42 
     [java]   549: getfield    0 
     [java]      | 42 220 
     [java]   552: invokevirtual 100 100 100 100 100 100 100 100 100 100 111 104 118 86 114 115 116 117 -1 
     [java]      | 42 
     [java]   170: enter       1 1 
     [java]      | 
     [java]   173: load_0      
     [java]      | 42 
     [java]   174: getfield    4 
     [java]      | 107 
     [java]   177: exit        
     [java]      | 107 
     [java]   178: return      
     [java]      | 107 
     [java]   593: const       107 
     [java]      | 107 107 
     [java]   598: jne         10 
     [java]      | 
     [java]   601: const       75 
     [java]      | 75 
     [java]   606: const_1     
     [java]      | 75 1 
     [java]   607: bprint      K
     [java]      | 
     [java]   608: const       10 
     [java]      | 10 
     [java]   613: const_1     
     [java]      | 10 1 
     [java]   614: bprint      
     [java] 
     [java]      | 
     [java]   615: load_0      
     [java]      | 42 
     [java]   616: load_0      
     [java]      | 42 42 
     [java]   617: getfield    0 
     [java]      | 42 220 
     [java]   620: invokevirtual 100 100 100 100 100 100 100 100 100 100 111 104 118 84 100 111 104 118 84 101 122 105 110 117 -1 
     [java]      | 42 
     [java]   181: enter       1 1 
     [java]      | 
     [java]   184: load_0      
     [java]      | 42 
     [java]   185: getfield    3 
     [java]      | 20 
     [java]   188: exit        
     [java]      | 20 
     [java]   189: return      
     [java]      | 20 
     [java]   665: const_5     
     [java]      | 20 5 
     [java]   666: print          20
     [java]      | 
     [java]   667: exit        
     [java]      | 
     [java]   668: return      
     [java]      | 
     [java]  4237: load_1      
     [java]      | 6 
     [java]  4238: pop         
     [java]      | 
     [java]  4239: inc         1 1 
     [java]      | 
     [java]  4242: load_1      
     [java]      | 7 
     [java]  4243: const       6 
     [java]      | 7 6 
     [java]  4248: jle         -124 
     [java]      | 
     [java]  4251: getstatic   1 
     [java]      | 4 
     [java]  4254: const_5     
     [java]      | 4 5 
     [java]  4255: print           4
     [java]      | 
     [java]  4256: const       10 
     [java]      | 10 
     [java]  4261: const_1     
     [java]      | 10 1 
     [java]  4262: bprint      
     [java] 
     [java]      | 
     [java]  4263: getstatic   0 
     [java]      | 90 
     [java]  4266: const_5     
     [java]      | 90 5 
     [java]  4267: print          90
     [java]      | 
     [java]  4268: const       10 
     [java]      | 10 
     [java]  4273: const_1     
     [java]      | 10 1 
     [java]  4274: bprint      
     [java] 
     [java]      | 
     [java]  4275: getstatic   3 
     [java]      | 80 
     [java]  4278: const_5     
     [java]      | 80 5 
     [java]  4279: print          80
     [java]      | 
     [java]  4280: const       10 
     [java]      | 10 
     [java]  4285: const_1     
     [java]      | 10 1 
     [java]  4286: bprint      
     [java] 
     [java]      | 
     [java]  4287: getstatic   2 
     [java]      | 1800 
     [java]  4290: const_5     
     [java]      | 1800 5 
     [java]  4291: print        1800
     [java]      | 
     [java]  4292: const       10 
     [java]      | 10 
     [java]  4297: const_1     
     [java]      | 10 1 
     [java]  4298: bprint      
     [java] 
     [java]      | 
     [java]  4299: const_0     
     [java]      | 0 
     [java]  4300: store_1     
     [java]      | 
     [java]  4301: load_1      
     [java]      | 0 
     [java]  4302: const_1     
     [java]      | 0 1 
     [java]  4303: add         
     [java]      | 1 
     [java]  4304: dup         
     [java]      | 1 1 
     [java]  4305: const_1     
     [java]      | 1 1 1 
     [java]  4306: jeq         40 
     [java]      | 1 
     [java]  4346: const_1     
     [java]      | 1 1 
     [java]  4347: const_5     
     [java]      | 1 1 5 
     [java]  4348: print           1
     [java]      | 1 
     [java]  4349: jmp         36 
     [java]      | 1 
     [java]  4385: const       10 
     [java]      | 1 10 
     [java]  4390: const_1     
     [java]      | 1 10 1 
     [java]  4391: bprint      
     [java] 
     [java]      | 1 
     [java]  4392: load_1      
     [java]      | 1 0 
     [java]  4393: pop         
     [java]      | 1 
     [java]  4394: inc         1 1 
     [java]      | 1 
     [java]  4397: load_1      
     [java]      | 1 1 
     [java]  4398: const       10 
     [java]      | 1 1 10 
     [java]  4403: jlt         -102 
     [java]      | 1 
     [java]  4301: load_1      
     [java]      | 1 1 
     [java]  4302: const_1     
     [java]      | 1 1 1 
     [java]  4303: add         
     [java]      | 1 2 
     [java]  4304: dup         
     [java]      | 1 2 2 
     [java]  4305: const_1     
     [java]      | 1 2 2 1 
     [java]  4306: jeq         40 
     [java]      | 1 2 
     [java]  4309: dup         
     [java]      | 1 2 2 
     [java]  4310: const_3     
     [java]      | 1 2 2 3 
     [java]  4311: jeq         41 
     [java]      | 1 2 
     [java]  4314: dup         
     [java]      | 1 2 2 
     [java]  4315: const_2     
     [java]      | 1 2 2 2 
     [java]  4316: jeq         39 
     [java]      | 1 2 
     [java]  4355: const_2     
     [java]      | 1 2 2 
     [java]  4356: const_5     
     [java]      | 1 2 2 5 
     [java]  4357: print           2
     [java]      | 1 2 
     [java]  4358: jmp         27 
     [java]      | 1 2 
     [java]  4385: const       10 
     [java]      | 1 2 10 
     [java]  4390: const_1     
     [java]      | 1 2 10 1 
     [java]  4391: bprint      
     [java] 
     [java]      | 1 2 
     [java]  4392: load_1      
     [java]      | 1 2 1 
     [java]  4393: pop         
     [java]      | 1 2 
     [java]  4394: inc         1 1 
     [java]      | 1 2 
     [java]  4397: load_1      
     [java]      | 1 2 2 
     [java]  4398: const       10 
     [java]      | 1 2 2 10 
     [java]  4403: jlt         -102 
     [java]      | 1 2 
     [java]  4301: load_1      
     [java]      | 1 2 2 
     [java]  4302: const_1     
     [java]      | 1 2 2 1 
     [java]  4303: add         
     [java]      | 1 2 3 
     [java]  4304: dup         
     [java]      | 1 2 3 3 
     [java]  4305: const_1     
     [java]      | 1 2 3 3 1 
     [java]  4306: jeq         40 
     [java]      | 1 2 3 
     [java]  4309: dup         
     [java]      | 1 2 3 3 
     [java]  4310: const_3     
     [java]      | 1 2 3 3 3 
     [java]  4311: jeq         41 
     [java]      | 1 2 3 
     [java]  4352: const_3     
     [java]      | 1 2 3 3 
     [java]  4353: const_5     
     [java]      | 1 2 3 3 5 
     [java]  4354: print           3
     [java]      | 1 2 3 
     [java]  4355: const_2     
     [java]      | 1 2 3 2 
     [java]  4356: const_5     
     [java]      | 1 2 3 2 5 
     [java]  4357: print           2
     [java]      | 1 2 3 
     [java]  4358: jmp         27 
     [java]      | 1 2 3 
     [java]  4385: const       10 
     [java]      | 1 2 3 10 
     [java]  4390: const_1     
     [java]      | 1 2 3 10 1 
     [java]  4391: bprint      
     [java] 
     [java]      | 1 2 3 
     [java]  4392: load_1      
     [java]      | 1 2 3 2 
     [java]  4393: pop         
     [java]      | 1 2 3 
     [java]  4394: inc         1 1 
     [java]      | 1 2 3 
     [java]  4397: load_1      
     [java]      | 1 2 3 3 
     [java]  4398: const       10 
     [java]      | 1 2 3 3 10 
     [java]  4403: jlt         -102 
     [java]      | 1 2 3 
     [java]  4301: load_1      
     [java]      | 1 2 3 3 
     [java]  4302: const_1     
     [java]      | 1 2 3 3 1 
     [java]  4303: add         
     [java]      | 1 2 3 4 
     [java]  4304: dup         
     [java]      | 1 2 3 4 4 
     [java]  4305: const_1     
     [java]      | 1 2 3 4 4 1 
     [java]  4306: jeq         40 
     [java]      | 1 2 3 4 
     [java]  4309: dup         
     [java]      | 1 2 3 4 4 
     [java]  4310: const_3     
     [java]      | 1 2 3 4 4 3 
     [java]  4311: jeq         41 
     [java]      | 1 2 3 4 
     [java]  4314: dup         
     [java]      | 1 2 3 4 4 
     [java]  4315: const_2     
     [java]      | 1 2 3 4 4 2 
     [java]  4316: jeq         39 
     [java]      | 1 2 3 4 
     [java]  4319: dup         
     [java]      | 1 2 3 4 4 
     [java]  4320: const_5     
     [java]      | 1 2 3 4 4 5 
     [java]  4321: jeq         40 
     [java]      | 1 2 3 4 
     [java]  4324: dup         
     [java]      | 1 2 3 4 4 
     [java]  4325: const       6 
     [java]      | 1 2 3 4 4 6 
     [java]  4330: jeq         41 
     [java]      | 1 2 3 4 
     [java]  4333: dup         
     [java]      | 1 2 3 4 4 
     [java]  4334: const       9 
     [java]      | 1 2 3 4 4 9 
     [java]  4339: jeq         39 
     [java]      | 1 2 3 4 
     [java]  4342: pop         
     [java]      | 1 2 3 
     [java]  4343: jmp         42 
     [java]      | 1 2 3 
     [java]  4385: const       10 
     [java]      | 1 2 3 10 
     [java]  4390: const_1     
     [java]      | 1 2 3 10 1 
     [java]  4391: bprint      
     [java] 
     [java]      | 1 2 3 
     [java]  4392: load_1      
     [java]      | 1 2 3 3 
     [java]  4393: pop         
     [java]      | 1 2 3 
     [java]  4394: inc         1 1 
     [java]      | 1 2 3 
     [java]  4397: load_1      
     [java]      | 1 2 3 4 
     [java]  4398: const       10 
     [java]      | 1 2 3 4 10 
     [java]  4403: jlt         -102 
     [java]      | 1 2 3 
     [java]  4301: load_1      
     [java]      | 1 2 3 4 
     [java]  4302: const_1     
     [java]      | 1 2 3 4 1 
     [java]  4303: add         
     [java]      | 1 2 3 5 
     [java]  4304: dup         
     [java]      | 1 2 3 5 5 
     [java]  4305: const_1     
     [java]      | 1 2 3 5 5 1 
     [java]  4306: jeq         40 
     [java]      | 1 2 3 5 
     [java]  4309: dup         
     [java]      | 1 2 3 5 5 
     [java]  4310: const_3     
     [java]      | 1 2 3 5 5 3 
     [java]  4311: jeq         41 
     [java]      | 1 2 3 5 
     [java]  4314: dup         
     [java]      | 1 2 3 5 5 
     [java]  4315: const_2     
     [java]      | 1 2 3 5 5 2 
     [java]  4316: jeq         39 
     [java]      | 1 2 3 5 
     [java]  4319: dup         
     [java]      | 1 2 3 5 5 
     [java]  4320: const_5     
     [java]      | 1 2 3 5 5 5 
     [java]  4321: jeq         40 
     [java]      | 1 2 3 5 
     [java]  4361: const_5     
     [java]      | 1 2 3 5 5 
     [java]  4362: const_5     
     [java]      | 1 2 3 5 5 5 
     [java]  4363: print           5
     [java]      | 1 2 3 5 
     [java]  4364: load_1      
     [java]      | 1 2 3 5 4 
     [java]  4365: const_2     
     [java]      | 1 2 3 5 4 2 
     [java]  4366: add         
     [java]      | 1 2 3 5 6 
     [java]  4367: store_1     
     [java]      | 1 2 3 5 
     [java]  4368: jmp         29 
     [java]      | 1 2 3 5 
     [java]  4397: load_1      
     [java]      | 1 2 3 5 6 
     [java]  4398: const       10 
     [java]      | 1 2 3 5 6 10 
     [java]  4403: jlt         -102 
     [java]      | 1 2 3 5 
     [java]  4301: load_1      
     [java]      | 1 2 3 5 6 
     [java]  4302: const_1     
     [java]      | 1 2 3 5 6 1 
     [java]  4303: add         
     [java]      | 1 2 3 5 7 
     [java]  4304: dup         
     [java]      | 1 2 3 5 7 7 
     [java]  4305: const_1     
     [java]      | 1 2 3 5 7 7 1 
     [java]  4306: jeq         40 
     [java]      | 1 2 3 5 7 
     [java]  4309: dup         
     [java]      | 1 2 3 5 7 7 
     [java]  4310: const_3     
     [java]      | 1 2 3 5 7 7 3 
     [java]  4311: jeq         41 
     [java]      | 1 2 3 5 7 
     [java]  4314: dup         
     [java]      | 1 2 3 5 7 7 
     [java]  4315: const_2     
     [java]      | 1 2 3 5 7 7 2 
     [java]  4316: jeq         39 
     [java]      | 1 2 3 5 7 
     [java]  4319: dup         
     [java]      | 1 2 3 5 7 7 
     [java]  4320: const_5     
     [java]      | 1 2 3 5 7 7 5 
     [java]  4321: jeq         40 
     [java]      | 1 2 3 5 7 
     [java]  4324: dup         
     [java]      | 1 2 3 5 7 7 
     [java]  4325: const       6 
     [java]      | 1 2 3 5 7 7 6 
     [java]  4330: jeq         41 
     [java]      | 1 2 3 5 7 
     [java]  4333: dup         
     [java]      | 1 2 3 5 7 7 
     [java]  4334: const       9 
     [java]      | 1 2 3 5 7 7 9 
     [java]  4339: jeq         39 
     [java]      | 1 2 3 5 7 
     [java]  4342: pop         
     [java]      | 1 2 3 5 
     [java]  4343: jmp         42 
     [java]      | 1 2 3 5 
     [java]  4385: const       10 
     [java]      | 1 2 3 5 10 
     [java]  4390: const_1     
     [java]      | 1 2 3 5 10 1 
     [java]  4391: bprint      
     [java] 
     [java]      | 1 2 3 5 
     [java]  4392: load_1      
     [java]      | 1 2 3 5 6 
     [java]  4393: pop         
     [java]      | 1 2 3 5 
     [java]  4394: inc         1 1 
     [java]      | 1 2 3 5 
     [java]  4397: load_1      
     [java]      | 1 2 3 5 7 
     [java]  4398: const       10 
     [java]      | 1 2 3 5 7 10 
     [java]  4403: jlt         -102 
     [java]      | 1 2 3 5 
     [java]  4301: load_1      
     [java]      | 1 2 3 5 7 
     [java]  4302: const_1     
     [java]      | 1 2 3 5 7 1 
     [java]  4303: add         
     [java]      | 1 2 3 5 8 
     [java]  4304: dup         
     [java]      | 1 2 3 5 8 8 
     [java]  4305: const_1     
     [java]      | 1 2 3 5 8 8 1 
     [java]  4306: jeq         40 
     [java]      | 1 2 3 5 8 
     [java]  4309: dup         
     [java]      | 1 2 3 5 8 8 
     [java]  4310: const_3     
     [java]      | 1 2 3 5 8 8 3 
     [java]  4311: jeq         41 
     [java]      | 1 2 3 5 8 
     [java]  4314: dup         
     [java]      | 1 2 3 5 8 8 
     [java]  4315: const_2     
     [java]      | 1 2 3 5 8 8 2 
     [java]  4316: jeq         39 
     [java]      | 1 2 3 5 8 
     [java]  4319: dup         
     [java]      | 1 2 3 5 8 8 
     [java]  4320: const_5     
     [java]      | 1 2 3 5 8 8 5 
     [java]  4321: jeq         40 
     [java]      | 1 2 3 5 8 
     [java]  4324: dup         
     [java]      | 1 2 3 5 8 8 
     [java]  4325: const       6 
     [java]      | 1 2 3 5 8 8 6 
     [java]  4330: jeq         41 
     [java]      | 1 2 3 5 8 
     [java]  4333: dup         
     [java]      | 1 2 3 5 8 8 
     [java]  4334: const       9 
     [java]      | 1 2 3 5 8 8 9 
     [java]  4339: jeq         39 
     [java]      | 1 2 3 5 8 
     [java]  4342: pop         
     [java]      | 1 2 3 5 
     [java]  4343: jmp         42 
     [java]      | 1 2 3 5 
     [java]  4385: const       10 
     [java]      | 1 2 3 5 10 
     [java]  4390: const_1     
     [java]      | 1 2 3 5 10 1 
     [java]  4391: bprint      
     [java] 
     [java]      | 1 2 3 5 
     [java]  4392: load_1      
     [java]      | 1 2 3 5 7 
     [java]  4393: pop         
     [java]      | 1 2 3 5 
     [java]  4394: inc         1 1 
     [java]      | 1 2 3 5 
     [java]  4397: load_1      
     [java]      | 1 2 3 5 8 
     [java]  4398: const       10 
     [java]      | 1 2 3 5 8 10 
     [java]  4403: jlt         -102 
     [java]      | 1 2 3 5 
     [java]  4301: load_1      
     [java]      | 1 2 3 5 8 
     [java]  4302: const_1     
     [java]      | 1 2 3 5 8 1 
     [java]  4303: add         
     [java]      | 1 2 3 5 9 
     [java]  4304: dup         
     [java]      | 1 2 3 5 9 9 
     [java]  4305: const_1     
     [java]      | 1 2 3 5 9 9 1 
     [java]  4306: jeq         40 
     [java]      | 1 2 3 5 9 
     [java]  4309: dup         
     [java]      | 1 2 3 5 9 9 
     [java]  4310: const_3     
     [java]      | 1 2 3 5 9 9 3 
     [java]  4311: jeq         41 
     [java]      | 1 2 3 5 9 
     [java]  4314: dup         
     [java]      | 1 2 3 5 9 9 
     [java]  4315: const_2     
     [java]      | 1 2 3 5 9 9 2 
     [java]  4316: jeq         39 
     [java]      | 1 2 3 5 9 
     [java]  4319: dup         
     [java]      | 1 2 3 5 9 9 
     [java]  4320: const_5     
     [java]      | 1 2 3 5 9 9 5 
     [java]  4321: jeq         40 
     [java]      | 1 2 3 5 9 
     [java]  4324: dup         
     [java]      | 1 2 3 5 9 9 
     [java]  4325: const       6 
     [java]      | 1 2 3 5 9 9 6 
     [java]  4330: jeq         41 
     [java]      | 1 2 3 5 9 
     [java]  4333: dup         
     [java]      | 1 2 3 5 9 9 
     [java]  4334: const       9 
     [java]      | 1 2 3 5 9 9 9 
     [java]  4339: jeq         39 
     [java]      | 1 2 3 5 9 
     [java]  4378: const       9 
     [java]      | 1 2 3 5 9 9 
     [java]  4383: const_5     
     [java]      | 1 2 3 5 9 9 5 
     [java]  4384: print           9
     [java]      | 1 2 3 5 9 
     [java]  4385: const       10 
     [java]      | 1 2 3 5 9 10 
     [java]  4390: const_1     
     [java]      | 1 2 3 5 9 10 1 
     [java]  4391: bprint      
     [java] 
     [java]      | 1 2 3 5 9 
     [java]  4392: load_1      
     [java]      | 1 2 3 5 9 8 
     [java]  4393: pop         
     [java]      | 1 2 3 5 9 
     [java]  4394: inc         1 1 
     [java]      | 1 2 3 5 9 
     [java]  4397: load_1      
     [java]      | 1 2 3 5 9 9 
     [java]  4398: const       10 
     [java]      | 1 2 3 5 9 9 10 
     [java]  4403: jlt         -102 
     [java]      | 1 2 3 5 9 
     [java]  4301: load_1      
     [java]      | 1 2 3 5 9 9 
     [java]  4302: const_1     
     [java]      | 1 2 3 5 9 9 1 
     [java]  4303: add         
     [java]      | 1 2 3 5 9 10 
     [java]  4304: dup         
     [java]      | 1 2 3 5 9 10 10 
     [java]  4305: const_1     
     [java]      | 1 2 3 5 9 10 10 1 
     [java]  4306: jeq         40 
     [java]      | 1 2 3 5 9 10 
     [java]  4309: dup         
     [java]      | 1 2 3 5 9 10 10 
     [java]  4310: const_3     
     [java]      | 1 2 3 5 9 10 10 3 
     [java]  4311: jeq         41 
     [java]      | 1 2 3 5 9 10 
     [java]  4314: dup         
     [java]      | 1 2 3 5 9 10 10 
     [java]  4315: const_2     
     [java]      | 1 2 3 5 9 10 10 2 
     [java]  4316: jeq         39 
     [java]      | 1 2 3 5 9 10 
     [java]  4319: dup         
     [java]      | 1 2 3 5 9 10 10 
     [java]  4320: const_5     
     [java]      | 1 2 3 5 9 10 10 5 
     [java]  4321: jeq         40 
     [java]      | 1 2 3 5 9 10 
     [java]  4324: dup         
     [java]      | 1 2 3 5 9 10 10 
     [java]  4325: const       6 
     [java]      | 1 2 3 5 9 10 10 6 
     [java]  4330: jeq         41 
     [java]      | 1 2 3 5 9 10 
     [java]  4333: dup         
     [java]      | 1 2 3 5 9 10 10 
     [java]  4334: const       9 
     [java]      | 1 2 3 5 9 10 10 9 
     [java]  4339: jeq         39 
     [java]      | 1 2 3 5 9 10 
     [java]  4342: pop         
     [java]      | 1 2 3 5 9 
     [java]  4343: jmp         42 
     [java]      | 1 2 3 5 9 
     [java]  4385: const       10 
     [java]      | 1 2 3 5 9 10 
     [java]  4390: const_1     
     [java]      | 1 2 3 5 9 10 1 
     [java]  4391: bprint      
     [java] 
     [java]      | 1 2 3 5 9 
     [java]  4392: load_1      
     [java]      | 1 2 3 5 9 9 
     [java]  4393: pop         
     [java]      | 1 2 3 5 9 
     [java]  4394: inc         1 1 
     [java]      | 1 2 3 5 9 
     [java]  4397: load_1      
     [java]      | 1 2 3 5 9 10 
     [java]  4398: const       10 
     [java]      | 1 2 3 5 9 10 10 
     [java]  4403: jlt         -102 
     [java]      | 1 2 3 5 9 
     [java]  4406: load_0      
     [java]      | 1 2 3 5 9 2 
     [java]  4407: const_0     
     [java]      | 1 2 3 5 9 2 0 
     [java]  4408: const_0     
     [java]      | 1 2 3 5 9 2 0 0 
     [java]  4409: astore      
     [java] Arraylength = 6
     [java] Address = 2
     [java] Index = 0
     [java] Value = 0
     [java] 
     [java]      | 1 2 3 5 9 
     [java]  4410: load_0      
     [java]      | 1 2 3 5 9 2 
     [java]  4411: const_0     
     [java]      | 1 2 3 5 9 2 0 
     [java]  4412: aload       
     [java]      | 1 2 3 5 9 0 
     [java]  4413: const_0     
     [java]      | 1 2 3 5 9 0 0 
     [java]  4414: jne         10 
     [java]      | 1 2 3 5 9 
     [java]  4417: const       69 
     [java]      | 1 2 3 5 9 69 
     [java]  4422: const_1     
     [java]      | 1 2 3 5 9 69 1 
     [java]  4423: bprint      E
     [java]      | 1 2 3 5 9 
     [java]  4424: new         20 
     [java]      | 1 2 3 5 9 69 
     [java]  4427: dup         
     [java]      | 1 2 3 5 9 69 69 
     [java]  4428: const_4     
     [java]      | 1 2 3 5 9 69 69 4 
     [java]  4429: putfield    0 
     [java]      | 1 2 3 5 9 69 
     [java]  4432: const_0     
     [java]      | 1 2 3 5 9 69 0 
     [java]  4433: jne         13 
     [java]      | 1 2 3 5 9 
     [java]  4446: const       75 
     [java]      | 1 2 3 5 9 75 
     [java]  4451: const_1     
     [java]      | 1 2 3 5 9 75 1 
     [java]  4452: bprint      K
     [java]      | 1 2 3 5 9 
     [java]  4453: const_0     
     [java]      | 1 2 3 5 9 0 
     [java]  4454: store_0     
     [java]      | 1 2 3 5 9 
     [java]  4455: load_0      
     [java]      | 1 2 3 5 9 0 
     [java]  4456: const_0     
     [java]      | 1 2 3 5 9 0 0 
     [java]  4457: jne         10 
     [java]      | 1 2 3 5 9 
     [java]  4460: const       78 
     [java]      | 1 2 3 5 9 78 
     [java]  4465: const_1     
     [java]      | 1 2 3 5 9 78 1 
     [java]  4466: bprint      N
     [java]      | 1 2 3 5 9 
     [java]  4467: const_0     
     [java]      | 1 2 3 5 9 0 
     [java]  4468: const_2     
     [java]      | 1 2 3 5 9 0 2 
     [java]  4469: newarray    1 
     [java]      | 1 2 3 5 9 0 75 
     [java]  4471: jne         10 
     [java]      | 1 2 3 5 9 
     [java]  4481: exit        
     [java]      | 1 2 3 5 9 
     [java]  4482: return      
     [java] Completion took 9187 ms

BUILD SUCCESSFUL
Total time: 9 seconds
